{"name":"BMW E46_M3_MSS54 hw1801_V4_Complete","version":" MSS54HP DME","baseAddress":0,"bigEndian":true,"parameters":[{"name":"Intake_TARGET 01 (16x16)","description":"KF_EVAN1_SOLL  1910\r\nHW:107 Version:211323001801JD34\r\nCreated by find routine V0.55\r\nBMWFlash/Galleto File Orientation [Slave Master]\r\nMatched Length:   MatchRatio: 0.31\r\nBlockFound: 1 NearbyBlockMatc","address":6416,"type":"MAP","dataType":"SBYTE","unit":"","min":-20.0,"max":80.0,"factor":1.0,"offset":0.0,"xAxis":{"type":"COM_AXIS","points":16,"min":0,"max":0,"unit":"","address":6352,"dataType":"UWORD","factor":1.0,"offset":0.0},"yAxis":{"type":"COM_AXIS","points":16,"min":0,"max":0,"unit":"","address":6384,"dataType":"UWORD","factor":0.0030517578125,"offset":0.0}},{"name":"Intake_TARGET 02 (16x16)","description":"KF_EVAN1_SOLL_KATH  1A52\r\nHW:107 Version:211323001801JD34\r\nCreated by find routine V0.55\r\nBMWFlash/Galleto File Orientation [Slave Master]\r\nMatched Length:   MatchRatio: 0.21\r\nBlockFound: 1 NearbyBloc","address":6738,"type":"MAP","dataType":"SBYTE","unit":"","min":-20.0,"max":80.0,"factor":1.0,"offset":0.0,"xAxis":{"type":"COM_AXIS","points":16,"min":0,"max":0,"unit":"","address":6674,"dataType":"UWORD","factor":1.0,"offset":0.0},"yAxis":{"type":"COM_AXIS","points":16,"min":0,"max":0,"unit":"","address":6706,"dataType":"UWORD","factor":0.0030517578125,"offset":0.0}},{"name":"Exhaust_TARGET 01 (16x16)","description":"KF_AVAN1_SOLL  1D78\r\nHW:107 Version:211323001801JD34\r\nCreated by find routine V0.55\r\nBMWFlash/Galleto File Orientation [Slave Master]\r\nMatched Length:   MatchRatio: 0.32\r\nBlockFound: 1 NearbyBlockMatc","address":7544,"type":"MAP","dataType":"SBYTE","unit":"","min":-20.0,"max":80.0,"factor":1.0,"offset":0.0,"xAxis":{"type":"COM_AXIS","points":16,"min":0,"max":0,"unit":"","address":7480,"dataType":"UWORD","factor":1.0,"offset":0.0},"yAxis":{"type":"COM_AXIS","points":16,"min":0,"max":0,"unit":"","address":7512,"dataType":"UWORD","factor":0.0030517578125,"offset":0.0}},{"name":"Exhaust_TARGET 02 (16x16)","description":"KF_AVAN1_SOLL_KATH  1EBA\r\nHW:107 Version:211323001801JD34\r\nCreated by find routine V0.55\r\nBMWFlash/Galleto File Orientation [Slave Master]\r\nMatched Length:   MatchRatio: 0.18\r\nBlockFound: 1 NearbyBloc","address":7866,"type":"MAP","dataType":"SBYTE","unit":"","min":-20.0,"max":80.0,"factor":1.0,"offset":0.0,"xAxis":{"type":"COM_AXIS","points":16,"min":0,"max":0,"unit":"","address":7802,"dataType":"UWORD","factor":1.0,"offset":0.0},"yAxis":{"type":"COM_AXIS","points":16,"min":0,"max":0,"unit":"","address":7834,"dataType":"UWORD","factor":0.0030517578125,"offset":0.0}},{"name":"KF_EVAN1_SOLL","description":"KF_EVAN1_SOLL  1910\r\nHW:107 Version:211323001801JD34\r\nCreated by find routine V0.55\r\nBMWFlash/Galleto File Orientation [Slave Master]\r\nMatched Length:   MatchRatio: 0.31\r\nBlockFound: 1 NearbyBlockMatc","address":6416,"type":"MAP","dataType":"SBYTE","unit":"","min":-20.0,"max":80.0,"factor":1.0,"offset":0.0,"xAxis":{"type":"COM_AXIS","points":16,"min":0,"max":0,"unit":"","address":6352,"dataType":"UWORD","factor":1.0,"offset":0.0},"yAxis":{"type":"COM_AXIS","points":16,"min":0,"max":0,"unit":"","address":6384,"dataType":"UWORD","factor":0.0030517578125,"offset":0.0}},{"name":"KF_EVAN1_SOLL_KATH","description":"KF_EVAN1_SOLL_KATH  1A52\r\nHW:107 Version:211323001801JD34\r\nCreated by find routine V0.55\r\nBMWFlash/Galleto File Orientation [Slave Master]\r\nMatched Length:   MatchRatio: 0.21\r\nBlockFound: 1 NearbyBloc","address":6738,"type":"MAP","dataType":"SBYTE","unit":"","min":-20.0,"max":80.0,"factor":1.0,"offset":0.0,"xAxis":{"type":"COM_AXIS","points":16,"min":0,"max":0,"unit":"","address":6674,"dataType":"UWORD","factor":1.0,"offset":0.0},"yAxis":{"type":"COM_AXIS","points":16,"min":0,"max":0,"unit":"","address":6706,"dataType":"UWORD","factor":0.0030517578125,"offset":0.0}},{"name":"KF_EVAN1_SOLL_DMAX","description":"KF_EVAN1_SOLL_DMAX  1CAE\r\nHW:107 Version:211323001801JD34\r\nCreated by find routine V0.55\r\nBMWFlash/Galleto File Orientation [Slave Master]\r\nMatched Length:   MatchRatio: 0.68\r\nBlockFound: 1 NearbyBloc","address":7342,"type":"MAP","dataType":"SWORD","unit":"","min":-20.0,"max":80.0,"factor":0.1,"offset":0.0,"xAxis":{"type":"COM_AXIS","points":6,"min":0,"max":0,"unit":"","address":7318,"dataType":"UWORD","factor":1.0,"offset":0.0},"yAxis":{"type":"COM_AXIS","points":6,"min":0,"max":0,"unit":"","address":7330,"dataType":"UWORD","factor":0.0030517578125,"offset":0.0}},{"name":"KF_AVAN1_SOLL","description":"KF_AVAN1_SOLL  1D78\r\nHW:107 Version:211323001801JD34\r\nCreated by find routine V0.55\r\nBMWFlash/Galleto File Orientation [Slave Master]\r\nMatched Length:   MatchRatio: 0.32\r\nBlockFound: 1 NearbyBlockMatc","address":7544,"type":"MAP","dataType":"SBYTE","unit":"","min":-20.0,"max":80.0,"factor":1.0,"offset":0.0,"xAxis":{"type":"COM_AXIS","points":16,"min":0,"max":0,"unit":"","address":7480,"dataType":"UWORD","factor":1.0,"offset":0.0},"yAxis":{"type":"COM_AXIS","points":16,"min":0,"max":0,"unit":"","address":7512,"dataType":"UWORD","factor":0.0030517578125,"offset":0.0}},{"name":"KF_AVAN1_SOLL_KATH","description":"KF_AVAN1_SOLL_KATH  1EBA\r\nHW:107 Version:211323001801JD34\r\nCreated by find routine V0.55\r\nBMWFlash/Galleto File Orientation [Slave Master]\r\nMatched Length:   MatchRatio: 0.18\r\nBlockFound: 1 NearbyBloc","address":7866,"type":"MAP","dataType":"SBYTE","unit":"","min":-20.0,"max":80.0,"factor":1.0,"offset":0.0,"xAxis":{"type":"COM_AXIS","points":16,"min":0,"max":0,"unit":"","address":7802,"dataType":"UWORD","factor":1.0,"offset":0.0},"yAxis":{"type":"COM_AXIS","points":16,"min":0,"max":0,"unit":"","address":7834,"dataType":"UWORD","factor":0.0030517578125,"offset":0.0}},{"name":"KF_AVAN1_SOLL_DMAX","description":"KF_AVAN1_SOLL_DMAX  2116\r\nHW:107 Version:211323001801JD34\r\nCreated by find routine V0.55\r\nBMWFlash/Galleto File Orientation [Slave Master]\r\nMatched Length:   MatchRatio: 0.57\r\nBlockFound: 1 NearbyBloc","address":8470,"type":"MAP","dataType":"SWORD","unit":"","min":-20.0,"max":80.0,"factor":0.1,"offset":0.0,"xAxis":{"type":"COM_AXIS","points":6,"min":0,"max":0,"unit":"","address":8446,"dataType":"UWORD","factor":1.0,"offset":0.0},"yAxis":{"type":"COM_AXIS","points":6,"min":0,"max":0,"unit":"","address":8458,"dataType":"UWORD","factor":0.0030517578125,"offset":0.0}}]}