{"name":"Subaru Subaru Liberty GT A2WD001G","version":"A2WD001G","verification":{"expected":"A2WD001G","position":2000},"baseAddress":0,"bigEndian":false,"parameters":[{"name":"Target Boost A","address":402372,"type":"MAP","dataType":"UWORD","unit":"Boost Target (psi relative sea level)","factor":0.01933677000000067,"offset":-14.6959452,"xAxis":{"type":"COM_AXIS","points":8,"min":0,"max":0,"unit":"","address":402292,"dataType":"UWORD","factor":1.0,"offset":0.0},"yAxis":{"type":"COM_AXIS","points":12,"min":0,"max":0,"unit":"","address":402324,"dataType":"UWORD","factor":1.0,"offset":0.0}},{"name":"Target Boost B","address":402644,"type":"MAP","dataType":"UWORD","unit":"Boost Target (psi relative sea level)","factor":0.01933677000000067,"offset":-14.6959452,"xAxis":{"type":"COM_AXIS","points":8,"min":0,"max":0,"unit":"","address":402564,"dataType":"UWORD","factor":1.0,"offset":0.0},"yAxis":{"type":"COM_AXIS","points":12,"min":0,"max":0,"unit":"","address":402596,"dataType":"UWORD","factor":1.0,"offset":0.0}},{"name":"Target Boost Compensation (ECT)","address":400284,"type":"CURVE","dataType":"UBYTE","unit":"Target Boost (psia) Compensation (%)","factor":0.78125,"offset":-100.0,"yAxis":{"type":"COM_AXIS","points":16,"min":0,"max":0,"unit":"","address":400028,"dataType":"UWORD","factor":1.0,"offset":0.0}},{"name":"Target Boost Compensation (1st Gear)","address":400024,"type":"CURVE","dataType":"FLOAT32","unit":"Target Boost (psia) Compensation (%)","factor":100.0,"offset":-100.0},{"name":"Target Boost Compensation (1st Gear) Speed Disable","address":400016,"type":"CURVE","dataType":"FLOAT32","unit":"Vehicle Speed (MPH)","factor":0.621,"offset":0.0},{"name":"Target Boost Compensation (Atm. Pressure) Multiplier","address":400540,"type":"CURVE","dataType":"UWORD","unit":"Atmospheric Pressure (psi) Multiplier","factor":0.00078910749,"offset":0.0,"yAxis":{"type":"COM_AXIS","points":4,"min":0,"max":0,"unit":"","address":400524,"dataType":"UWORD","factor":1.0,"offset":0.0}},{"name":"Target Boost Compensation (Atm. Pressure) Multiplier Offset","address":400332,"type":"CURVE","dataType":"UBYTE","unit":"Atmospheric Pressure Multiplier Offset","factor":0.015625,"offset":-2.0,"yAxis":{"type":"COM_AXIS","points":4,"min":0,"max":0,"unit":"","address":400316,"dataType":"UWORD","factor":1.0,"offset":0.0}},{"name":"Boost Limit (Fuel Cut)","address":421076,"type":"CURVE","dataType":"UWORD","unit":"psi absolute","factor":0.01933677,"offset":0.0,"yAxis":{"type":"COM_AXIS","points":6,"min":0,"max":0,"unit":"","address":421052,"dataType":"UWORD","factor":1.0,"offset":0.0}},{"name":"Boost Control Disable (IAM)","address":399992,"type":"CURVE","dataType":"FLOAT32","unit":"Ignition Advance Multiplier (IAM)","factor":1.0,"offset":0.0},{"name":"Boost Control Disable (Fine Correction)","address":399988,"type":"CURVE","dataType":"FLOAT32","unit":"Current Fine Correction Learning (degrees of correction)","factor":1.0,"offset":0.0},{"name":"Boost Control Disable Delay (Fine Correction)","address":399905,"type":"CURVE","dataType":"UBYTE","unit":"counter threshold","factor":1.0,"offset":0.0},{"name":"Initial Wastegate Duty A","address":400900,"type":"MAP","dataType":"UWORD","unit":"Wastegate Duty Cycle (%)","factor":0.00390625,"offset":0.0,"xAxis":{"type":"COM_AXIS","points":8,"min":0,"max":0,"unit":"","address":400820,"dataType":"UWORD","factor":1.0,"offset":0.0},"yAxis":{"type":"COM_AXIS","points":12,"min":0,"max":0,"unit":"","address":400852,"dataType":"UWORD","factor":1.0,"offset":0.0}},{"name":"Initial Wastegate Duty B","address":401172,"type":"MAP","dataType":"UWORD","unit":"Wastegate Duty Cycle (%)","factor":0.00390625,"offset":0.0,"xAxis":{"type":"COM_AXIS","points":8,"min":0,"max":0,"unit":"","address":401092,"dataType":"UWORD","factor":1.0,"offset":0.0},"yAxis":{"type":"COM_AXIS","points":12,"min":0,"max":0,"unit":"","address":401124,"dataType":"UWORD","factor":1.0,"offset":0.0}},{"name":"Max Wastegate Duty","address":401972,"type":"MAP","dataType":"UWORD","unit":"Wastegate Duty Cycle (%)","factor":0.00390625,"offset":0.0,"xAxis":{"type":"COM_AXIS","points":8,"min":0,"max":0,"unit":"","address":401908,"dataType":"UWORD","factor":1.0,"offset":0.0},"yAxis":{"type":"COM_AXIS","points":8,"min":0,"max":0,"unit":"","address":401940,"dataType":"UWORD","factor":1.0,"offset":0.0}},{"name":"Max Wastegate Duty Limit Post-Compensation","address":86056,"type":"CURVE","dataType":"FLOAT32","unit":"Wastegate Duty Cycle (%)","factor":1.0,"offset":0.0},{"name":"Initial/Max Wastegate Duty Compensation (IAT)","address":400156,"type":"CURVE","dataType":"UBYTE","unit":"Initial/Max Wastegate Duty Compensation (% relative)","factor":0.78125,"offset":-100.0,"yAxis":{"type":"COM_AXIS","points":16,"min":0,"max":0,"unit":"","address":400092,"dataType":"UWORD","factor":1.0,"offset":0.0}},{"name":"Initial/Max Wastegate Duty Compensation (ECT)","address":400252,"type":"CURVE","dataType":"UBYTE","unit":"Initial/Max Wastegate Duty Compensation (% relative)","factor":0.78125,"offset":-100.0,"yAxis":{"type":"COM_AXIS","points":16,"min":0,"max":0,"unit":"","address":400028,"dataType":"UWORD","factor":1.0,"offset":0.0}},{"name":"Initial/Max Wastegate Duty Compensation (Atm. Pressure)","address":400732,"type":"MAP","dataType":"UBYTE","unit":"Initial/Max Wastegate Duty Compensation (% relative)","factor":0.78125,"offset":-100.0,"xAxis":{"type":"COM_AXIS","points":6,"min":0,"max":0,"unit":"","address":400692,"dataType":"UWORD","factor":1.0,"offset":0.0},"yAxis":{"type":"COM_AXIS","points":4,"min":0,"max":0,"unit":"","address":400716,"dataType":"UWORD","factor":1.0,"offset":0.0}},{"name":"Turbo Dynamics Proportional","address":400392,"type":"CURVE","dataType":"UWORD","unit":"Wastegate Duty Correction (% absolute)","factor":0.00390625,"offset":-50.0,"yAxis":{"type":"COM_AXIS","points":9,"min":0,"max":0,"unit":"","address":400356,"dataType":"UWORD","factor":1.0,"offset":0.0}},{"name":"Turbo Dynamics Integral Positive","address":400504,"type":"CURVE","dataType":"UWORD","unit":"Wastegate Duty Correction (% absolute)","factor":0.00390625,"offset":-50.0,"yAxis":{"type":"COM_AXIS","points":9,"min":0,"max":0,"unit":"","address":400468,"dataType":"UWORD","factor":1.0,"offset":0.0}},{"name":"Turbo Dynamics Integral Negative","address":400448,"type":"CURVE","dataType":"UWORD","unit":"Wastegate Duty Correction (% absolute)","factor":0.00390625,"offset":-50.0,"yAxis":{"type":"COM_AXIS","points":9,"min":0,"max":0,"unit":"","address":400412,"dataType":"UWORD","factor":1.0,"offset":0.0}},{"name":"TD Activation Thresholds (RPM)","address":399960,"type":"CURVE","dataType":"FLOAT32","unit":"Engine Speed (RPM)","factor":1.0,"offset":0.0},{"name":"TD Activation Thresholds (Target Boost)","address":399916,"type":"CURVE","dataType":"FLOAT32","unit":"Target Boost (psi relative sea level)","factor":0.01933677000000067,"offset":-14.6959452},{"name":"TD Integral Cumulative Range (WGDC Correction)","address":399976,"type":"CURVE","dataType":"FLOAT32","unit":"TD Integral Cumulative Wastegate Duty Correction (% absolute)","factor":1.0,"offset":0.0},{"name":"TD Integral Negative Activation (Boost Error)","address":399932,"type":"CURVE","dataType":"FLOAT32","unit":"Boost Error (psi)","factor":0.01933677,"offset":0.0},{"name":"TD Integral Positive Activation (Boost Error)","address":399940,"type":"CURVE","dataType":"FLOAT32","unit":"Boost Error (psi)","factor":0.01933677,"offset":0.0},{"name":"TD Integral Positive Activation (Wastegate Duty)","address":399948,"type":"CURVE","dataType":"FLOAT32","unit":"Wastegate Duty Cycle (%)","factor":1.0,"offset":0.0},{"name":"Manifold Pressure Sensor Scaling","address":398616,"type":"CURVE","dataType":"FLOAT32","unit":"psi absolute","factor":0.01933677,"offset":0.0},{"name":"Manifold Pressure Sensor Limits (CEL)","address":443252,"type":"CURVE","dataType":"UWORD","unit":"Volts","factor":7.6293945e-05,"offset":0.0},{"name":"Manifold Pressure Sensor CEL Delays","address":415229,"type":"CURVE","dataType":"UBYTE","unit":"counter threshold","factor":1.0,"offset":0.0},{"name":"Primary Open Loop Fueling A","address":422300,"type":"MAP","dataType":"UBYTE","unit":"Estimated Air/Fuel Ratio","factor":-0.1139534883720934,"offset":14.7,"xAxis":{"type":"COM_AXIS","points":16,"min":0,"max":0,"unit":"","address":422164,"dataType":"UWORD","factor":1.0,"offset":0.0},"yAxis":{"type":"COM_AXIS","points":18,"min":0,"max":0,"unit":"","address":422228,"dataType":"UWORD","factor":1.0,"offset":0.0}},{"name":"Primary Open Loop Fueling B","address":422724,"type":"MAP","dataType":"UBYTE","unit":"Estimated Air/Fuel Ratio","factor":-0.1139534883720934,"offset":14.7,"xAxis":{"type":"COM_AXIS","points":16,"min":0,"max":0,"unit":"","address":422588,"dataType":"UWORD","factor":1.0,"offset":0.0},"yAxis":{"type":"COM_AXIS","points":18,"min":0,"max":0,"unit":"","address":422652,"dataType":"UWORD","factor":1.0,"offset":0.0}},{"name":"Primary Open Loop Fueling A (Failsafe)","address":423148,"type":"MAP","dataType":"UBYTE","unit":"Estimated Air/Fuel Ratio","factor":-0.1139534883720934,"offset":14.7,"xAxis":{"type":"COM_AXIS","points":16,"min":0,"max":0,"unit":"","address":423012,"dataType":"UWORD","factor":1.0,"offset":0.0},"yAxis":{"type":"COM_AXIS","points":18,"min":0,"max":0,"unit":"","address":423076,"dataType":"UWORD","factor":1.0,"offset":0.0}},{"name":"Primary Open Loop Fueling B (Failsafe)","address":423572,"type":"MAP","dataType":"UBYTE","unit":"Estimated Air/Fuel Ratio","factor":-0.1139534883720934,"offset":14.7,"xAxis":{"type":"COM_AXIS","points":16,"min":0,"max":0,"unit":"","address":423436,"dataType":"UWORD","factor":1.0,"offset":0.0},"yAxis":{"type":"COM_AXIS","points":18,"min":0,"max":0,"unit":"","address":423500,"dataType":"UWORD","factor":1.0,"offset":0.0}},{"name":"Primary Open Loop Fuel Map Switch (IAM)","address":417144,"type":"CURVE","dataType":"FLOAT32","unit":"Ignition Advance Multiplier (IAM)","factor":1.0,"offset":0.0},{"name":"Minimum Active Primary Open Loop Enrichment","address":416988,"type":"CURVE","dataType":"FLOAT32","unit":"Estimated Air/Fuel Ratio","factor":-7.35,"offset":14.7},{"name":"Minimum Primary Open Loop Enrichment (Throttle)","address":418688,"type":"CURVE","dataType":"UBYTE","unit":"Estimated Primary Open Loop Air/Fuel Ratio Lean Limit","factor":-0.057198443579766334,"offset":14.7,"yAxis":{"type":"COM_AXIS","points":6,"min":0,"max":0,"unit":"","address":418664,"dataType":"UWORD","factor":1.0,"offset":0.0}},{"name":"Primary Open Loop Fueling Compensation (ECT)","address":420724,"type":"CURVE","dataType":"UWORD","unit":"'Primary Open Loop Fueling' Enrichment Offset Compensation (%)","factor":0.003051757999998017,"offset":-100.0,"yAxis":{"type":"COM_AXIS","points":16,"min":0,"max":0,"unit":"","address":417876,"dataType":"UWORD","factor":1.0,"offset":0.0}},{"name":"Primary Open Loop Fueling Compensation (Timing Compensation) ","address":418720,"type":"CURVE","dataType":"UBYTE","unit":"'Primary Open Loop Fueling' Raw Enrichment Offset Additive","factor":0.0078125,"offset":0.0,"yAxis":{"type":"COM_AXIS","points":6,"min":0,"max":0,"unit":"","address":418696,"dataType":"UWORD","factor":1.0,"offset":0.0}},{"name":"Front Oxygen Sensor Scaling","address":444928,"type":"CURVE","dataType":"FLOAT32","unit":"Air/Fuel Ratio","factor":14.7,"offset":0.0,"yAxis":{"type":"COM_AXIS","points":13,"min":0,"max":0,"unit":"","address":444876,"dataType":"UWORD","factor":1.0,"offset":0.0}},{"name":"Front Oxygen Sensor Rich Limit","address":138288,"type":"CURVE","dataType":"FLOAT32","unit":"Air/Fuel Ratio","factor":14.7,"offset":0.0},{"name":"Front Oxygen Sensor Compensation (Atm. Pressure)","address":412252,"type":"CURVE","dataType":"UWORD","unit":"Front Oxygen Sensor Compensation","factor":3.051758e-05,"offset":0.0,"yAxis":{"type":"COM_AXIS","points":4,"min":0,"max":0,"unit":"","address":412236,"dataType":"UWORD","factor":1.0,"offset":0.0}},{"name":"CL Fueling Target Compensation (Load)","address":425200,"type":"MAP","dataType":"UWORD","unit":"Estimated Air/Fuel Ratio Points (Additive)","factor":0.000224304212999904,"offset":-7.35,"xAxis":{"type":"COM_AXIS","points":8,"min":0,"max":0,"unit":"","address":425128,"dataType":"UWORD","factor":1.0,"offset":0.0},"yAxis":{"type":"COM_AXIS","points":10,"min":0,"max":0,"unit":"","address":425160,"dataType":"UWORD","factor":1.0,"offset":0.0}},{"name":"CL Fueling Target Compensation (ECT) ","address":419930,"type":"CURVE","dataType":"UWORD","unit":"Estimated Air/Fuel Ratio Points (Additive)","factor":-0.000224304212999904,"offset":7.350001,"yAxis":{"type":"COM_AXIS","points":16,"min":0,"max":0,"unit":"","address":417876,"dataType":"UWORD","factor":1.0,"offset":0.0}},{"name":"CL to OL Delay","address":416182,"type":"CURVE","dataType":"UWORD","unit":"counter threshold","factor":1.0,"offset":0.0},{"name":"CL to OL Transition with Delay A (Throttle)","address":418488,"type":"CURVE","dataType":"UBYTE","unit":"Throttle Plate Opening Angle (%)","factor":0.581287202,"offset":0.0,"yAxis":{"type":"COM_AXIS","points":16,"min":0,"max":0,"unit":"","address":418424,"dataType":"UWORD","factor":1.0,"offset":0.0}},{"name":"CL to OL Transition with Delay B (Throttle)","address":418568,"type":"CURVE","dataType":"UBYTE","unit":"Throttle Plate Opening Angle (%)","factor":0.581287202,"offset":0.0,"yAxis":{"type":"COM_AXIS","points":16,"min":0,"max":0,"unit":"","address":418504,"dataType":"UWORD","factor":1.0,"offset":0.0}},{"name":"CL to OL Transition with Delay C (Throttle)","address":418648,"type":"CURVE","dataType":"UBYTE","unit":"Throttle Plate Opening Angle (%)","factor":0.581287202,"offset":0.0,"yAxis":{"type":"COM_AXIS","points":16,"min":0,"max":0,"unit":"","address":418584,"dataType":"UWORD","factor":1.0,"offset":0.0}},{"name":"CL to OL Transition with Delay Throttle Hysteresis","address":416992,"type":"CURVE","dataType":"FLOAT32","unit":"Throttle Plate Opening Angle (%)","factor":1.1904761904761905,"offset":0.0},{"name":"CL to OL Transition with Delay A (Base Pulse Width)","address":420500,"type":"CURVE","dataType":"UWORD","unit":"Base Pulse Width (ms)","factor":0.004,"offset":0.0,"yAxis":{"type":"COM_AXIS","points":16,"min":0,"max":0,"unit":"","address":420436,"dataType":"UWORD","factor":1.0,"offset":0.0}},{"name":"CL to OL Transition with Delay B (Base Pulse Width)","address":420596,"type":"CURVE","dataType":"UWORD","unit":"Base Pulse Width (ms)","factor":0.004,"offset":0.0,"yAxis":{"type":"COM_AXIS","points":16,"min":0,"max":0,"unit":"","address":420532,"dataType":"UWORD","factor":1.0,"offset":0.0}},{"name":"CL to OL Transition with Delay C (Base Pulse Width)","address":420692,"type":"CURVE","dataType":"UWORD","unit":"Base Pulse Width (ms)","factor":0.004,"offset":0.0,"yAxis":{"type":"COM_AXIS","points":16,"min":0,"max":0,"unit":"","address":420628,"dataType":"UWORD","factor":1.0,"offset":0.0}},{"name":"CL to OL Transition with Delay BPW Hysteresis","address":416996,"type":"CURVE","dataType":"FLOAT32","unit":"Base Pulse Width (ms)","factor":0.001,"offset":0.0},{"name":"CL Delay Maximum (Vehicle Speed)","address":417112,"type":"CURVE","dataType":"FLOAT32","unit":"Vehicle Speed (MPH)","factor":0.621,"offset":0.0},{"name":"CL Delay Minimum (ECT)","address":417000,"type":"CURVE","dataType":"FLOAT32","unit":"Coolant Temp (Degrees F)","factor":1.7999999999999972,"offset":32.0},{"name":"CL Delay Maximum Engine Speed (Per Gear)","address":417004,"type":"CURVE","dataType":"FLOAT32","unit":"Engine Speed (RPM)","factor":1.0,"offset":0.0},{"name":"CL Delay Maximum Engine Speed (Neutral)","address":417084,"type":"CURVE","dataType":"FLOAT32","unit":"Engine Speed (RPM)","factor":1.0,"offset":0.0},{"name":"CL Delay Throttle Atm. Pressure Thresholds","address":417128,"type":"CURVE","dataType":"FLOAT32","unit":"Atmospheric Pressure (psi)","factor":0.01933677,"offset":0.0},{"name":"CL Delay Maximum (Throttle) (Low Atm. Pressure)","address":417100,"type":"CURVE","dataType":"FLOAT32","unit":"Throttle Plate Opening Angle (%)","factor":1.1904761904761905,"offset":0.0},{"name":"CL Delay Maximum (Throttle) (High Atm. Pressure)","address":417092,"type":"CURVE","dataType":"FLOAT32","unit":"Throttle Plate Opening Angle (%)","factor":1.1904761904761905,"offset":0.0},{"name":"Injector Latency","address":443520,"type":"CURVE","dataType":"UWORD","unit":"Latency (ms)","factor":0.00025,"offset":0.0,"yAxis":{"type":"COM_AXIS","points":5,"min":0,"max":0,"unit":"","address":443500,"dataType":"UWORD","factor":1.0,"offset":0.0}},{"name":"Injector Flow Scaling","address":416628,"type":"CURVE","dataType":"FLOAT32","unit":"ESTIMATED Flow Rate - Gas Only (cc/min)","factor":-1353545.0,"offset":4060635.0},{"name":"Per Injector Primary Fuel Offset Compensation A","address":423920,"type":"MAP","dataType":"UBYTE","unit":"Injector Fuel Offset Additive","factor":0.0078125,"offset":-1.0,"xAxis":{"type":"COM_AXIS","points":8,"min":0,"max":0,"unit":"","address":423860,"dataType":"UWORD","factor":1.0,"offset":0.0},"yAxis":{"type":"COM_AXIS","points":7,"min":0,"max":0,"unit":"","address":423892,"dataType":"UWORD","factor":1.0,"offset":0.0}},{"name":"Per Injector Primary Fuel Offset Compensation B","address":424036,"type":"MAP","dataType":"UBYTE","unit":"Injector Fuel Offset Additive","factor":0.0078125,"offset":-1.0,"xAxis":{"type":"COM_AXIS","points":8,"min":0,"max":0,"unit":"","address":423976,"dataType":"UWORD","factor":1.0,"offset":0.0},"yAxis":{"type":"COM_AXIS","points":7,"min":0,"max":0,"unit":"","address":424008,"dataType":"UWORD","factor":1.0,"offset":0.0}},{"name":"Per Injector Primary Fuel Offset Compensation C","address":424152,"type":"MAP","dataType":"UBYTE","unit":"Injector Fuel Offset Additive","factor":0.0078125,"offset":-1.0,"xAxis":{"type":"COM_AXIS","points":8,"min":0,"max":0,"unit":"","address":424092,"dataType":"UWORD","factor":1.0,"offset":0.0},"yAxis":{"type":"COM_AXIS","points":7,"min":0,"max":0,"unit":"","address":424124,"dataType":"UWORD","factor":1.0,"offset":0.0}},{"name":"Per Injector Primary Fuel Offset Compensation D","address":424268,"type":"MAP","dataType":"UBYTE","unit":"Injector Fuel Offset Additive","factor":0.0078125,"offset":-1.0,"xAxis":{"type":"COM_AXIS","points":8,"min":0,"max":0,"unit":"","address":424208,"dataType":"UWORD","factor":1.0,"offset":0.0},"yAxis":{"type":"COM_AXIS","points":7,"min":0,"max":0,"unit":"","address":424240,"dataType":"UWORD","factor":1.0,"offset":0.0}},{"name":"Cranking Fuel Injector Pulse Width A (ECT)","address":419158,"type":"CURVE","dataType":"UWORD","unit":"Injector Pulse Width (ms)","factor":0.008,"offset":0.0,"yAxis":{"type":"COM_AXIS","points":16,"min":0,"max":0,"unit":"","address":417876,"dataType":"UWORD","factor":1.0,"offset":0.0}},{"name":"Cranking Fuel Injector Pulse Width B (ECT)","address":419190,"type":"CURVE","dataType":"UWORD","unit":"Injector Pulse Width (ms)","factor":0.008,"offset":0.0,"yAxis":{"type":"COM_AXIS","points":16,"min":0,"max":0,"unit":"","address":417876,"dataType":"UWORD","factor":1.0,"offset":0.0}},{"name":"Cranking Fuel Injector Pulse Width C (ECT)","address":419222,"type":"CURVE","dataType":"UWORD","unit":"Injector Pulse Width (ms)","factor":0.008,"offset":0.0,"yAxis":{"type":"COM_AXIS","points":16,"min":0,"max":0,"unit":"","address":417876,"dataType":"UWORD","factor":1.0,"offset":0.0}},{"name":"Cranking Fuel Injector Pulse Width D (ECT)","address":419254,"type":"CURVE","dataType":"UWORD","unit":"Injector Pulse Width (ms)","factor":0.008,"offset":0.0,"yAxis":{"type":"COM_AXIS","points":16,"min":0,"max":0,"unit":"","address":417876,"dataType":"UWORD","factor":1.0,"offset":0.0}},{"name":"Cranking Fuel IPW Compensation (RPM)","address":421792,"type":"MAP","dataType":"UBYTE","unit":"Cranking Fuel Injector Pulse Width Compensation (%)","factor":0.78125,"offset":-100.0,"xAxis":{"type":"COM_AXIS","points":5,"min":0,"max":0,"unit":"","address":421744,"dataType":"UWORD","factor":1.0,"offset":0.0},"yAxis":{"type":"COM_AXIS","points":7,"min":0,"max":0,"unit":"","address":421764,"dataType":"UWORD","factor":1.0,"offset":0.0}},{"name":"Cranking Fuel IPW Compensation (Accelerator)","address":418028,"type":"CURVE","dataType":"UBYTE","unit":"Cranking Fuel Injector Pulse Width Compensation (%)","factor":0.78125,"offset":-100.0,"yAxis":{"type":"COM_AXIS","points":6,"min":0,"max":0,"unit":"","address":418004,"dataType":"UWORD","factor":1.0,"offset":0.0}},{"name":"Throttle Tip-in Enrichment","address":420984,"type":"CURVE","dataType":"UWORD","unit":"Additional Injector Pulse Width (ms)","factor":0.004,"offset":0.0,"yAxis":{"type":"COM_AXIS","points":17,"min":0,"max":0,"unit":"","address":420916,"dataType":"UWORD","factor":1.0,"offset":0.0}},{"name":"Minimum Tip-in Enrichment Activation","address":417320,"type":"CURVE","dataType":"FLOAT32","unit":"Additional Injector Pulse Width (ms)","factor":0.004,"offset":0.0},{"name":"Minimum Tip-in Enrichment Activation (Throttle)","address":417316,"type":"CURVE","dataType":"FLOAT32","unit":"Throttle Angle Change (%)","factor":1.0,"offset":0.0},{"name":"Tip-in Enrichment Compensation (Boost Error)","address":418836,"type":"CURVE","dataType":"UBYTE","unit":"Throttle Tip-in Enrichment Compensation (%)","factor":0.78125,"offset":-100.0,"yAxis":{"type":"COM_AXIS","points":9,"min":0,"max":0,"unit":"","address":418800,"dataType":"UWORD","factor":1.0,"offset":0.0}},{"name":"Tip-in Enrichment Compensation (ECT)","address":421018,"type":"CURVE","dataType":"UWORD","unit":"Throttle Tip-in Enrichment Compensation (%)","factor":0.01220703125,"offset":-100.0,"yAxis":{"type":"COM_AXIS","points":16,"min":0,"max":0,"unit":"","address":417876,"dataType":"UWORD","factor":1.0,"offset":0.0}},{"name":"Tip-in Enrichment Disable Applied Counter Threshold","address":416135,"type":"CURVE","dataType":"UBYTE","unit":"tip-in enrichment applied counter","factor":1.0,"offset":0.0},{"name":"Tip-in Enrichment Applied Counter Reset","address":416136,"type":"CURVE","dataType":"UBYTE","unit":"tip-in last applied counter period","factor":1.0,"offset":0.0},{"name":"Tip-in Enrichment Disable Throttle Cumulative Threshold","address":417324,"type":"CURVE","dataType":"FLOAT32","unit":"cumulative throttle angle change","factor":1.0,"offset":0.0},{"name":"Tip-in Throttle Cumulative Reset","address":416137,"type":"CURVE","dataType":"UBYTE","unit":"tip-in last applied counter period","factor":1.0,"offset":0.0},{"name":"Min Primary Base Enrichment 1","address":418114,"type":"CURVE","dataType":"UBYTE","unit":"Minimum Primary Enrichment Offset Additive 1","factor":0.00390625,"offset":0.0,"yAxis":{"type":"COM_AXIS","points":16,"min":0,"max":0,"unit":"","address":417876,"dataType":"UWORD","factor":1.0,"offset":0.0}},{"name":"Min Primary Base Enrichment 1 (Non-Primary OL)","address":422132,"type":"MAP","dataType":"UBYTE","unit":"Minimum Primary Enrichment Offset Additive 1","factor":0.00390625,"offset":0.0,"xAxis":{"type":"COM_AXIS","points":10,"min":0,"max":0,"unit":"","address":422080,"dataType":"UWORD","factor":1.0,"offset":0.0},"yAxis":{"type":"COM_AXIS","points":3,"min":0,"max":0,"unit":"","address":422120,"dataType":"UWORD","factor":1.0,"offset":0.0}},{"name":"Min Primary Base Enrich 2 Initial Start 1A","address":419414,"type":"CURVE","dataType":"UWORD","unit":"Initial Afterstart Offset","factor":0.0002441406,"offset":0.0,"yAxis":{"type":"COM_AXIS","points":16,"min":0,"max":0,"unit":"","address":417876,"dataType":"UWORD","factor":1.0,"offset":0.0}},{"name":"Min Primary Base Enrich 2 Initial Start 1B","address":419478,"type":"CURVE","dataType":"UWORD","unit":"Initial Afterstart Offset","factor":0.0002441406,"offset":0.0,"yAxis":{"type":"COM_AXIS","points":16,"min":0,"max":0,"unit":"","address":417876,"dataType":"UWORD","factor":1.0,"offset":0.0}},{"name":"Min Primary Base Enrich 2 Initial Start 2A","address":419446,"type":"CURVE","dataType":"UWORD","unit":"Initial Afterstart Offset","factor":0.0002441406,"offset":0.0,"yAxis":{"type":"COM_AXIS","points":16,"min":0,"max":0,"unit":"","address":417876,"dataType":"UWORD","factor":1.0,"offset":0.0}},{"name":"Min Primary Base Enrich 2 Initial Start 2B","address":419510,"type":"CURVE","dataType":"UWORD","unit":"Initial Afterstart Offset","factor":0.0002441406,"offset":0.0,"yAxis":{"type":"COM_AXIS","points":16,"min":0,"max":0,"unit":"","address":417876,"dataType":"UWORD","factor":1.0,"offset":0.0}},{"name":"Min Primary Base Enrich 2 Decay Step 1","address":419542,"type":"CURVE","dataType":"UWORD","unit":"Decay Step Value","factor":9.536743e-07,"offset":0.0,"yAxis":{"type":"COM_AXIS","points":16,"min":0,"max":0,"unit":"","address":417876,"dataType":"UWORD","factor":1.0,"offset":0.0}},{"name":"Min Primary Base Enrich 2 Decay Step 2","address":419574,"type":"CURVE","dataType":"UWORD","unit":"Decay Step Value","factor":9.536743e-07,"offset":0.0,"yAxis":{"type":"COM_AXIS","points":16,"min":0,"max":0,"unit":"","address":417876,"dataType":"UWORD","factor":1.0,"offset":0.0}},{"name":"Min Primary Base Enrich 3 Initial Start 1A","address":419286,"type":"CURVE","dataType":"UWORD","unit":"Initial Afterstart Offset","factor":0.00390625,"offset":0.0,"yAxis":{"type":"COM_AXIS","points":16,"min":0,"max":0,"unit":"","address":417876,"dataType":"UWORD","factor":1.0,"offset":0.0}},{"name":"Min Primary Base Enrich 3 Initial Start 1B","address":419318,"type":"CURVE","dataType":"UWORD","unit":"Initial Afterstart Offset","factor":0.00390625,"offset":0.0,"yAxis":{"type":"COM_AXIS","points":16,"min":0,"max":0,"unit":"","address":417876,"dataType":"UWORD","factor":1.0,"offset":0.0}},{"name":"Min Primary Base Enrich 3 Initial Start 2A","address":419350,"type":"CURVE","dataType":"UWORD","unit":"Initial Afterstart Offset","factor":0.00390625,"offset":0.0,"yAxis":{"type":"COM_AXIS","points":16,"min":0,"max":0,"unit":"","address":417876,"dataType":"UWORD","factor":1.0,"offset":0.0}},{"name":"Min Primary Base Enrich 3 Initial Start 2B","address":419382,"type":"CURVE","dataType":"UWORD","unit":"Initial Afterstart Offset","factor":0.00390625,"offset":0.0,"yAxis":{"type":"COM_AXIS","points":16,"min":0,"max":0,"unit":"","address":417876,"dataType":"UWORD","factor":1.0,"offset":0.0}},{"name":"Min Primary Base Enrich 3 Decay Delay A","address":418050,"type":"CURVE","dataType":"UBYTE","unit":"Period in-between decay multiplier application","factor":1.0,"offset":0.0,"yAxis":{"type":"COM_AXIS","points":16,"min":0,"max":0,"unit":"","address":417876,"dataType":"UWORD","factor":1.0,"offset":0.0}},{"name":"Min Primary Base Enrich 3 Decay Delay B","address":418066,"type":"CURVE","dataType":"UBYTE","unit":"Period in-between decay multiplier application","factor":1.0,"offset":0.0,"yAxis":{"type":"COM_AXIS","points":16,"min":0,"max":0,"unit":"","address":417876,"dataType":"UWORD","factor":1.0,"offset":0.0}},{"name":"Min Primary Base Enrich 3 Decay Multiplier","address":416632,"type":"CURVE","dataType":"FLOAT32","unit":"Multiplier","factor":1.0,"offset":0.0},{"name":"A/F Learning #1 Limits","address":416904,"type":"CURVE","dataType":"FLOAT32","unit":"A/F Learning #1 Limits (%)","factor":100.0,"offset":0.0},{"name":"A/F Learning #1 Airflow Ranges","address":416916,"type":"CURVE","dataType":"FLOAT32","unit":"Mass Airflow (g/s)","factor":1.0,"offset":0.0},{"name":"MAF Limit (Maximum)","address":411576,"type":"CURVE","dataType":"FLOAT32","unit":"Mass Airflow (g/s)","factor":1.0,"offset":0.0},{"name":"MAF Sensor Scaling","address":444420,"type":"CURVE","dataType":"FLOAT32","unit":"Mass Airflow (g/s)","factor":1.0,"offset":0.0,"yAxis":{"type":"COM_AXIS","points":54,"min":0,"max":0,"unit":"","address":444204,"dataType":"UWORD","factor":1.0,"offset":0.0}},{"name":"MAF Compensation (IAT)","address":413900,"type":"MAP","dataType":"UBYTE","unit":"Mass Airflow Compensation (%)","factor":0.390625,"offset":-50.0,"xAxis":{"type":"COM_AXIS","points":5,"min":0,"max":0,"unit":"","address":413848,"dataType":"UWORD","factor":1.0,"offset":0.0},"yAxis":{"type":"COM_AXIS","points":8,"min":0,"max":0,"unit":"","address":413868,"dataType":"UWORD","factor":1.0,"offset":0.0}},{"name":"Engine Load Limit (Maximum)","address":131404,"type":"CURVE","dataType":"FLOAT32","unit":"Engine Load (g/rev)","factor":1.0,"offset":0.0},{"name":"Engine Load Compensation (MP)","address":413716,"type":"MAP","dataType":"UBYTE","unit":"Engine Load Compensation (%)","factor":0.390625,"offset":-50.0,"xAxis":{"type":"COM_AXIS","points":11,"min":0,"max":0,"unit":"","address":413624,"dataType":"UWORD","factor":1.0,"offset":0.0},"yAxis":{"type":"COM_AXIS","points":12,"min":0,"max":0,"unit":"","address":413668,"dataType":"UWORD","factor":1.0,"offset":0.0}},{"name":"Base Timing A","address":429828,"type":"MAP","dataType":"UBYTE","unit":"Base Ignition Timing (degrees BTDC)","factor":0.3515625,"offset":-20.0,"xAxis":{"type":"COM_AXIS","points":17,"min":0,"max":0,"unit":"","address":429688,"dataType":"UWORD","factor":1.0,"offset":0.0},"yAxis":{"type":"COM_AXIS","points":18,"min":0,"max":0,"unit":"","address":429756,"dataType":"UWORD","factor":1.0,"offset":0.0}},{"name":"Base Timing B","address":430276,"type":"MAP","dataType":"UBYTE","unit":"Base Ignition Timing (degrees BTDC)","factor":0.3515625,"offset":-20.0,"xAxis":{"type":"COM_AXIS","points":17,"min":0,"max":0,"unit":"","address":430136,"dataType":"UWORD","factor":1.0,"offset":0.0},"yAxis":{"type":"COM_AXIS","points":18,"min":0,"max":0,"unit":"","address":430204,"dataType":"UWORD","factor":1.0,"offset":0.0}},{"name":"Base Timing Idle","address":427645,"type":"CURVE","dataType":"UBYTE","unit":"Base Ignition Timing (degrees BTDC)","factor":0.3515625,"offset":-20.0,"yAxis":{"type":"COM_AXIS","points":16,"min":0,"max":0,"unit":"","address":427256,"dataType":"UWORD","factor":1.0,"offset":0.0}},{"name":"Base Timing Idle Minimum","address":427636,"type":"CURVE","dataType":"UBYTE","unit":"Base Ignition Timing (degrees BTDC)","factor":0.3515625,"offset":-20.0,"yAxis":{"type":"COM_AXIS","points":9,"min":0,"max":0,"unit":"","address":427600,"dataType":"UWORD","factor":1.0,"offset":0.0}},{"name":"Base Timing Idle Minimum Vehicle Speed Enable","address":426556,"type":"CURVE","dataType":"FLOAT32","unit":"Vehicle Speed (MPH)","factor":0.621,"offset":0.0},{"name":"Knock Correction Advance Max A","address":431012,"type":"MAP","dataType":"UBYTE","unit":"Maximum Knock Correction Timing Advance (degrees)","factor":0.3515625,"offset":0.0,"xAxis":{"type":"COM_AXIS","points":17,"min":0,"max":0,"unit":"","address":430872,"dataType":"UWORD","factor":1.0,"offset":0.0},"yAxis":{"type":"COM_AXIS","points":18,"min":0,"max":0,"unit":"","address":430940,"dataType":"UWORD","factor":1.0,"offset":0.0}},{"name":"Knock Correction Advance Max B","address":431460,"type":"MAP","dataType":"UBYTE","unit":"Maximum Knock Correction Timing Advance (degrees)","factor":0.3515625,"offset":0.0,"xAxis":{"type":"COM_AXIS","points":17,"min":0,"max":0,"unit":"","address":431320,"dataType":"UWORD","factor":1.0,"offset":0.0},"yAxis":{"type":"COM_AXIS","points":18,"min":0,"max":0,"unit":"","address":431388,"dataType":"UWORD","factor":1.0,"offset":0.0}},{"name":"Timing Compensation (IAT)","address":427760,"type":"CURVE","dataType":"UBYTE","unit":"Ignition Timing Correction (degrees)","factor":0.3515625,"offset":-45.0,"yAxis":{"type":"COM_AXIS","points":16,"min":0,"max":0,"unit":"","address":427696,"dataType":"UWORD","factor":1.0,"offset":0.0}},{"name":"Timing Compensation (IAT) Activation","address":430648,"type":"MAP","dataType":"UBYTE","unit":"Timing Compensation Intake Temp Map Target Compensation (%)","factor":0.78125,"offset":-100.0,"xAxis":{"type":"COM_AXIS","points":8,"min":0,"max":0,"unit":"","address":430584,"dataType":"UWORD","factor":1.0,"offset":0.0},"yAxis":{"type":"COM_AXIS","points":8,"min":0,"max":0,"unit":"","address":430616,"dataType":"UWORD","factor":1.0,"offset":0.0}},{"name":"Timing Compensation (ECT)","address":427677,"type":"CURVE","dataType":"UBYTE","unit":"Ignition Timing Correction (degrees)","factor":0.3515625,"offset":-45.0,"yAxis":{"type":"COM_AXIS","points":16,"min":0,"max":0,"unit":"","address":427256,"dataType":"UWORD","factor":1.0,"offset":0.0}},{"name":"Timing Compensation (MRP)","address":431820,"type":"MAP","dataType":"UBYTE","unit":"Ignition Timing Correction (degrees)","factor":0.3515625,"offset":-45.0,"xAxis":{"type":"COM_AXIS","points":5,"min":0,"max":0,"unit":"","address":431788,"dataType":"UWORD","factor":1.0,"offset":0.0},"yAxis":{"type":"COM_AXIS","points":3,"min":0,"max":0,"unit":"","address":431808,"dataType":"UWORD","factor":1.0,"offset":0.0}},{"name":"Timing Compensation Per Cylinder A  ","address":428088,"type":"CURVE","dataType":"UBYTE","unit":"Ignition Timing Correction (degrees)","factor":0.3515625,"offset":-45.0,"yAxis":{"type":"COM_AXIS","points":14,"min":0,"max":0,"unit":"","address":428032,"dataType":"UWORD","factor":1.0,"offset":0.0}},{"name":"Timing Compensation Per Cylinder B  ","address":428160,"type":"CURVE","dataType":"UBYTE","unit":"Ignition Timing Correction (degrees)","factor":0.3515625,"offset":-45.0,"yAxis":{"type":"COM_AXIS","points":14,"min":0,"max":0,"unit":"","address":428104,"dataType":"UWORD","factor":1.0,"offset":0.0}},{"name":"Timing Compensation Per Cylinder C  ","address":428232,"type":"CURVE","dataType":"UBYTE","unit":"Ignition Timing Correction (degrees)","factor":0.3515625,"offset":-45.0,"yAxis":{"type":"COM_AXIS","points":14,"min":0,"max":0,"unit":"","address":428176,"dataType":"UWORD","factor":1.0,"offset":0.0}},{"name":"Timing Compensation Per Cylinder D  ","address":428304,"type":"CURVE","dataType":"UBYTE","unit":"Ignition Timing Correction (degrees)","factor":0.3515625,"offset":-45.0,"yAxis":{"type":"COM_AXIS","points":14,"min":0,"max":0,"unit":"","address":428248,"dataType":"UWORD","factor":1.0,"offset":0.0}},{"name":"Timing Comp Minimum Load (Per Cylinder)","address":426712,"type":"CURVE","dataType":"FLOAT32","unit":"Engine Load (g/rev)","factor":1.0,"offset":0.0},{"name":"Timing Comp Maximum RPM (Per Cylinder)","address":426708,"type":"CURVE","dataType":"FLOAT32","unit":"Engine Speed (RPM)","factor":1.0,"offset":0.0},{"name":"Timing Comp Minimum Coolant Temp (Per Cylinder)","address":426716,"type":"CURVE","dataType":"FLOAT32","unit":"Coolant Temp (Degrees F)","factor":1.7999999999999972,"offset":32.0},{"name":"Feedback Correction Range (RPM)","address":426768,"type":"CURVE","dataType":"FLOAT32","unit":"Engine Speed (RPM)","factor":1.0,"offset":0.0},{"name":"Feedback Correction Minimum Load","address":426784,"type":"CURVE","dataType":"FLOAT32","unit":"Engine Load (g/rev)","factor":1.0,"offset":0.0},{"name":"Feedback Correction Retard Value","address":426736,"type":"CURVE","dataType":"FLOAT32","unit":"degrees of correction","factor":-1.0,"offset":0.0},{"name":"Feedback Correction Retard Limit","address":426732,"type":"CURVE","dataType":"FLOAT32","unit":"degrees of correction","factor":-1.0,"offset":0.0},{"name":"Feedback Correction Negative Advance Value","address":426744,"type":"CURVE","dataType":"FLOAT32","unit":"degrees of correction","factor":1.0,"offset":0.0},{"name":"Feedback Correction Negative Advance Delay","address":426326,"type":"CURVE","dataType":"UWORD","unit":"counter threshold","factor":1.0,"offset":0.0},{"name":"Extended Feedback Correction High RPM Compensation","address":426792,"type":"CURVE","dataType":"FLOAT32","unit":"multiplier","factor":1.0,"offset":0.0},{"name":"Fine Correction Range (RPM)","address":427016,"type":"CURVE","dataType":"FLOAT32","unit":"Engine Speed (RPM)","factor":1.0,"offset":0.0},{"name":"Fine Correction Range (Load)","address":427032,"type":"CURVE","dataType":"FLOAT32","unit":"Engine Load (g/rev)","factor":1.0,"offset":0.0},{"name":"Fine Correction Rows (RPM)","address":427064,"type":"CURVE","dataType":"FLOAT32","unit":"Engine Speed (RPM)","factor":1.0,"offset":0.0},{"name":"Fine Correction Columns (Load)","address":427048,"type":"CURVE","dataType":"FLOAT32","unit":"Engine Load (g/rev)","factor":1.0,"offset":0.0},{"name":"Fine Correction Retard Value","address":427088,"type":"CURVE","dataType":"FLOAT32","unit":"degrees of correction","factor":-1.0,"offset":0.0},{"name":"Fine Correction Retard Limit","address":427008,"type":"CURVE","dataType":"FLOAT32","unit":"degrees of correction","factor":1.0,"offset":0.0},{"name":"Fine Correction Advance Value","address":427012,"type":"CURVE","dataType":"FLOAT32","unit":"degrees of correction","factor":1.0,"offset":0.0},{"name":"Fine Correction Advance Limit","address":427004,"type":"CURVE","dataType":"FLOAT32","unit":"degrees of correction","factor":1.0,"offset":0.0},{"name":"Fine Correction Advance Delay","address":426340,"type":"CURVE","dataType":"UWORD","unit":"counter threshold","factor":1.0,"offset":0.0},{"name":"Rough Correction Range (RPM)","address":426912,"type":"CURVE","dataType":"FLOAT32","unit":"Engine Speed (RPM)","factor":1.0,"offset":0.0},{"name":"Rough Correction Range (Load)","address":426928,"type":"CURVE","dataType":"FLOAT32","unit":"Engine Load (g/rev)","factor":1.0,"offset":0.0},{"name":"Rough Correction Minimum KC Advance Map Value","address":426944,"type":"CURVE","dataType":"FLOAT32","unit":"Current 'Knock Correction Advance Max' Map Value (degrees)","factor":1.0,"offset":0.0},{"name":"Rough Correction Learning Delay (Increasing)","address":428360,"type":"CURVE","dataType":"UBYTE","unit":"Rough Correction (IAM) Positive Learning Delay (counter threshold)","factor":1.0,"offset":0.0,"yAxis":{"type":"COM_AXIS","points":10,"min":0,"max":0,"unit":"","address":428320,"dataType":"UWORD","factor":1.0,"offset":0.0}},{"name":"Advance Multiplier (Initial)","address":426908,"type":"CURVE","dataType":"FLOAT32","unit":"Ignition Advance Multiplier (IAM)","factor":1.0,"offset":0.0},{"name":"Advance Multiplier Step Value","address":426948,"type":"CURVE","dataType":"FLOAT32","unit":"change in multiplier","factor":1.0,"offset":0.0},{"name":"Intake Cam Advance Angle A (AVCS)","address":450288,"type":"MAP","dataType":"UWORD","unit":"Advance (degrees)","factor":0.0054931640625,"offset":0.0,"xAxis":{"type":"COM_AXIS","points":14,"min":0,"max":0,"unit":"","address":450160,"dataType":"UWORD","factor":1.0,"offset":0.0},"yAxis":{"type":"COM_AXIS","points":18,"min":0,"max":0,"unit":"","address":450216,"dataType":"UWORD","factor":1.0,"offset":0.0}},{"name":"Intake Cam Advance Angle B (AVCS)","address":450920,"type":"MAP","dataType":"UWORD","unit":"Advance (degrees)","factor":0.0054931640625,"offset":0.0,"xAxis":{"type":"COM_AXIS","points":14,"min":0,"max":0,"unit":"","address":450792,"dataType":"UWORD","factor":1.0,"offset":0.0},"yAxis":{"type":"COM_AXIS","points":18,"min":0,"max":0,"unit":"","address":450848,"dataType":"UWORD","factor":1.0,"offset":0.0}},{"name":"Exhaust Cam Retard Angle A (AVCS)","address":452632,"type":"MAP","dataType":"UWORD","unit":"Retard (degrees)","factor":0.0054931640625,"offset":0.0,"xAxis":{"type":"COM_AXIS","points":14,"min":0,"max":0,"unit":"","address":452504,"dataType":"UWORD","factor":1.0,"offset":0.0},"yAxis":{"type":"COM_AXIS","points":18,"min":0,"max":0,"unit":"","address":452560,"dataType":"UWORD","factor":1.0,"offset":0.0}},{"name":"Exhaust Cam Retard Angle B (AVCS)","address":453264,"type":"MAP","dataType":"UWORD","unit":"Retard (degrees)","factor":0.0054931640625,"offset":0.0,"xAxis":{"type":"COM_AXIS","points":14,"min":0,"max":0,"unit":"","address":453136,"dataType":"UWORD","factor":1.0,"offset":0.0},"yAxis":{"type":"COM_AXIS","points":18,"min":0,"max":0,"unit":"","address":453192,"dataType":"UWORD","factor":1.0,"offset":0.0}},{"name":"Requested Torque (Accelerator Pedal)","address":439492,"type":"MAP","dataType":"UWORD","unit":"Requested Torque (raw ecu value)","factor":0.0078125,"offset":0.0,"xAxis":{"type":"COM_AXIS","points":20,"min":0,"max":0,"unit":"","address":439344,"dataType":"UWORD","factor":1.0,"offset":0.0},"yAxis":{"type":"COM_AXIS","points":17,"min":0,"max":0,"unit":"","address":439424,"dataType":"UWORD","factor":1.0,"offset":0.0}},{"name":"Target Throttle Plate Position A (Requested Torque)","address":438124,"type":"MAP","dataType":"UWORD","unit":"Target Throttle Plate Opening Angle (%)","factor":0.002270655357,"offset":0.0,"xAxis":{"type":"COM_AXIS","points":17,"min":0,"max":0,"unit":"","address":437992,"dataType":"UWORD","factor":1.0,"offset":0.0},"yAxis":{"type":"COM_AXIS","points":16,"min":0,"max":0,"unit":"","address":438060,"dataType":"UWORD","factor":1.0,"offset":0.0}},{"name":"Target Throttle Plate Position B (Requested Torque)","address":438800,"type":"MAP","dataType":"UWORD","unit":"Target Throttle Plate Opening Angle (%)","factor":0.002270655357,"offset":0.0,"xAxis":{"type":"COM_AXIS","points":17,"min":0,"max":0,"unit":"","address":438668,"dataType":"UWORD","factor":1.0,"offset":0.0},"yAxis":{"type":"COM_AXIS","points":16,"min":0,"max":0,"unit":"","address":438736,"dataType":"UWORD","factor":1.0,"offset":0.0}},{"name":"Rev Limit (Fuel Cut)","address":417520,"type":"CURVE","dataType":"FLOAT32","unit":"Engine Speed (RPM)","factor":1.0,"offset":0.0},{"name":"Rev Limit Fuel Resume (Boost)","address":417528,"type":"CURVE","dataType":"FLOAT32","unit":"Manifold Pressure (psi relative sea level)","factor":0.01933677000000067,"offset":-14.6959452},{"name":"Speed Limiting Enable (Fuel Cut)","address":417392,"type":"CURVE","dataType":"FLOAT32","unit":"Vehicle Speed (MPH)","factor":0.621,"offset":0.0},{"name":"Speed Limiting Disable (Fuel Cut)","address":417400,"type":"CURVE","dataType":"FLOAT32","unit":"Vehicle Speed (MPH)","factor":0.621,"offset":0.0},{"name":"Speed Limiting (Throttle)","address":412224,"type":"CURVE","dataType":"FLOAT32","unit":"Vehicle Speed (MPH)","factor":0.621,"offset":0.0},{"name":"Intake Temp Sensor Scaling","address":398036,"type":"CURVE","dataType":"FLOAT32","unit":"Temperature (Degrees F)","factor":1.7999999999999972,"offset":32.0,"yAxis":{"type":"COM_AXIS","points":30,"min":0,"max":0,"unit":"","address":397916,"dataType":"UWORD","factor":1.0,"offset":0.0}},{"name":"Coolant Temp Sensor Scaling","address":397804,"type":"CURVE","dataType":"FLOAT32","unit":"Temperature (Degrees F)","factor":1.7999999999999972,"offset":32.0,"yAxis":{"type":"COM_AXIS","points":28,"min":0,"max":0,"unit":"","address":397692,"dataType":"UWORD","factor":1.0,"offset":0.0}},{"name":"Atmospheric Pressure Sensor Scaling","address":398532,"type":"CURVE","dataType":"FLOAT32","unit":"psi","factor":0.01933677,"offset":0.0},{"name":"Radiator Fan Modes (ECT)","address":446808,"type":"CURVE","dataType":"FLOAT32","unit":"Coolant Temp (Degrees F)","factor":1.7999999999999972,"offset":32.0},{"name":"Radiator Fan Modes (Veh. Speed)","address":446824,"type":"CURVE","dataType":"FLOAT32","unit":"Vehicle Speed (MPH)","factor":0.621,"offset":0.0},{"name":"Idle Speed Target A","address":435038,"type":"CURVE","dataType":"UWORD","unit":"Engine Speed (RPM)","factor":0.1953125,"offset":0.0,"yAxis":{"type":"COM_AXIS","points":16,"min":0,"max":0,"unit":"","address":433604,"dataType":"UWORD","factor":1.0,"offset":0.0}},{"name":"Idle Speed Target B","address":435102,"type":"CURVE","dataType":"UWORD","unit":"Engine Speed (RPM)","factor":0.1953125,"offset":0.0,"yAxis":{"type":"COM_AXIS","points":16,"min":0,"max":0,"unit":"","address":433604,"dataType":"UWORD","factor":1.0,"offset":0.0}},{"name":"Idle Speed Target C","address":435166,"type":"CURVE","dataType":"UWORD","unit":"Engine Speed (RPM)","factor":0.1953125,"offset":0.0,"yAxis":{"type":"COM_AXIS","points":16,"min":0,"max":0,"unit":"","address":433604,"dataType":"UWORD","factor":1.0,"offset":0.0}}]}