{"name":"Subaru Subaru Forester XT AZ1G105L","version":"AZ1G105L","verification":{"expected":"AZ1G105L","position":8196},"baseAddress":0,"bigEndian":false,"parameters":[{"name":"Target Boost ","address":790208,"type":"MAP","dataType":"UWORD","unit":"Boost Target (psi relative sea level)","factor":0.01933677000000067,"offset":-14.6959452,"xAxis":{"type":"COM_AXIS","points":11,"min":0,"max":0,"unit":"","address":790104,"dataType":"UWORD","factor":1.0,"offset":0.0},"yAxis":{"type":"COM_AXIS","points":15,"min":0,"max":0,"unit":"","address":790148,"dataType":"UWORD","factor":1.0,"offset":0.0},"rows":15,"cols":11},{"name":"Target Boost Compensation (ECT)","address":788448,"type":"CURVE","dataType":"UBYTE","unit":"Target Boost (psia) Compensation (%)","factor":0.78125,"offset":-100.0,"yAxis":{"type":"COM_AXIS","points":16,"min":0,"max":0,"unit":"","address":788224,"dataType":"UWORD","factor":1.0,"offset":0.0},"rows":1,"cols":16},{"name":"Target Boost Compensation (1st Gear)","address":788216,"type":"CURVE","dataType":"FLOAT32","unit":"Target Boost (psia) Compensation (%)","factor":100.0,"offset":-100.0,"rows":1,"cols":1},{"name":"Target Boost Compensation (1st Gear) Speed Disable","address":788212,"type":"CURVE","dataType":"FLOAT32","unit":"Vehicle Speed (MPH)","factor":0.621,"offset":0.0,"rows":1,"cols":1},{"name":"Target Boost Compensation (IAT) ","address":788776,"type":"CURVE","dataType":"FLOAT32","unit":"Target Boost (psia) Compensation (%)","factor":100.0,"offset":-100.0,"yAxis":{"type":"COM_AXIS","points":6,"min":0,"max":0,"unit":"","address":788752,"dataType":"UWORD","factor":1.0,"offset":0.0},"rows":1,"cols":6},{"name":"Target Boost Compensation (Atm. Pressure) ","address":788924,"type":"MAP","dataType":"UBYTE","unit":"Target Boost (psia) Compensation (%)","factor":0.78125,"offset":-100.0,"xAxis":{"type":"COM_AXIS","points":6,"min":0,"max":0,"unit":"","address":788876,"dataType":"UWORD","factor":1.0,"offset":0.0},"yAxis":{"type":"COM_AXIS","points":6,"min":0,"max":0,"unit":"","address":788900,"dataType":"UWORD","factor":1.0,"offset":0.0},"rows":6,"cols":6},{"name":"Boost Limit (Fuel Cut) ","address":840440,"type":"MAP","dataType":"UWORD","unit":"psi absolute","factor":0.01933677,"offset":0.0,"xAxis":{"type":"COM_AXIS","points":6,"min":0,"max":0,"unit":"","address":840372,"dataType":"UWORD","factor":1.0,"offset":0.0},"yAxis":{"type":"COM_AXIS","points":11,"min":0,"max":0,"unit":"","address":840396,"dataType":"UWORD","factor":1.0,"offset":0.0},"rows":11,"cols":6},{"name":"Boost Control Disable (IAM)","address":788200,"type":"CURVE","dataType":"FLOAT32","unit":"Ignition Advance Multiplier (IAM)","factor":1.0,"offset":0.0,"rows":1,"cols":2},{"name":"Boost Control Disable (Fine Correction)","address":788196,"type":"CURVE","dataType":"FLOAT32","unit":"Current Fine Correction Learning (degrees of correction)","factor":1.0,"offset":0.0,"rows":1,"cols":1},{"name":"Boost Control Disable Delay (Fine Correction)","address":788121,"type":"CURVE","dataType":"UBYTE","unit":"counter threshold","factor":1.0,"offset":0.0,"rows":1,"cols":1},{"name":"Initial Wastegate Duty ","address":789652,"type":"MAP","dataType":"UWORD","unit":"Wastegate Duty Cycle (%)","factor":0.00390625,"offset":0.0,"xAxis":{"type":"COM_AXIS","points":15,"min":0,"max":0,"unit":"","address":789532,"dataType":"UWORD","factor":1.0,"offset":0.0},"yAxis":{"type":"COM_AXIS","points":15,"min":0,"max":0,"unit":"","address":789592,"dataType":"UWORD","factor":1.0,"offset":0.0},"rows":15,"cols":15},{"name":"Max Wastegate Duty ","address":789080,"type":"MAP","dataType":"UWORD","unit":"Wastegate Duty Cycle (%)","factor":0.00390625,"offset":0.0,"xAxis":{"type":"COM_AXIS","points":15,"min":0,"max":0,"unit":"","address":788960,"dataType":"UWORD","factor":1.0,"offset":0.0},"yAxis":{"type":"COM_AXIS","points":15,"min":0,"max":0,"unit":"","address":789020,"dataType":"UWORD","factor":1.0,"offset":0.0},"rows":15,"cols":15},{"name":"Max Wastegate Duty Limit Post-Compensation","address":83756,"type":"CURVE","dataType":"FLOAT32","unit":"Wastegate Duty Cycle (%)","factor":1.0,"offset":0.0,"rows":1,"cols":1},{"name":"Initial/Max Wastegate Duty Compensation (IAT)","address":788352,"type":"CURVE","dataType":"UBYTE","unit":"Initial/Max Wastegate Duty Compensation (% relative)","factor":0.78125,"offset":-100.0,"yAxis":{"type":"COM_AXIS","points":16,"min":0,"max":0,"unit":"","address":788288,"dataType":"UWORD","factor":1.0,"offset":0.0},"rows":1,"cols":16},{"name":"Initial/Max Wastegate Duty Compensation (ECT)","address":788384,"type":"CURVE","dataType":"UBYTE","unit":"Initial/Max Wastegate Duty Compensation (% relative)","factor":0.78125,"offset":-100.0,"yAxis":{"type":"COM_AXIS","points":16,"min":0,"max":0,"unit":"","address":788224,"dataType":"UWORD","factor":1.0,"offset":0.0},"rows":1,"cols":16},{"name":"Initial/Max Wastegate Duty Compensation (Atm. Pressure)","address":788844,"type":"MAP","dataType":"UBYTE","unit":"Initial/Max Wastegate Duty Compensation (% relative)","factor":0.78125,"offset":-100.0,"xAxis":{"type":"COM_AXIS","points":6,"min":0,"max":0,"unit":"","address":788800,"dataType":"UWORD","factor":1.0,"offset":0.0},"yAxis":{"type":"COM_AXIS","points":5,"min":0,"max":0,"unit":"","address":788824,"dataType":"UWORD","factor":1.0,"offset":0.0},"rows":5,"cols":6},{"name":"Turbo Dynamics Proportional","address":788500,"type":"CURVE","dataType":"UWORD","unit":"Wastegate Duty Correction (% absolute)","factor":0.00390625,"offset":-50.0,"yAxis":{"type":"COM_AXIS","points":9,"min":0,"max":0,"unit":"","address":788464,"dataType":"UWORD","factor":1.0,"offset":0.0},"rows":1,"cols":9},{"name":"Turbo Dynamics Integral Positive","address":788612,"type":"CURVE","dataType":"UWORD","unit":"Wastegate Duty Correction (% absolute)","factor":0.00390625,"offset":-50.0,"yAxis":{"type":"COM_AXIS","points":9,"min":0,"max":0,"unit":"","address":788576,"dataType":"UWORD","factor":1.0,"offset":0.0},"rows":1,"cols":9},{"name":"Turbo Dynamics Integral Negative","address":788556,"type":"CURVE","dataType":"UWORD","unit":"Wastegate Duty Correction (% absolute)","factor":0.00390625,"offset":-50.0,"yAxis":{"type":"COM_AXIS","points":9,"min":0,"max":0,"unit":"","address":788520,"dataType":"UWORD","factor":1.0,"offset":0.0},"rows":1,"cols":9},{"name":"TD Proportional Compensation (IAT)","address":788400,"type":"CURVE","dataType":"UBYTE","unit":"TD Proportional Map Target Compensation (% relative)","factor":0.78125,"offset":-100.0,"yAxis":{"type":"COM_AXIS","points":16,"min":0,"max":0,"unit":"","address":788288,"dataType":"UWORD","factor":1.0,"offset":0.0},"rows":1,"cols":16},{"name":"TD Integral Positive Compensation (IAT)","address":788432,"type":"CURVE","dataType":"UBYTE","unit":"TD Integral Positive Map Target Compensation (% relative)","factor":0.78125,"offset":-100.0,"yAxis":{"type":"COM_AXIS","points":16,"min":0,"max":0,"unit":"","address":788288,"dataType":"UWORD","factor":1.0,"offset":0.0},"rows":1,"cols":16},{"name":"TD Integral Negative Compensation (IAT)","address":788416,"type":"CURVE","dataType":"UBYTE","unit":"TD Integral Negative Map Target Compensation (% relative)","factor":0.78125,"offset":-100.0,"yAxis":{"type":"COM_AXIS","points":16,"min":0,"max":0,"unit":"","address":788288,"dataType":"UWORD","factor":1.0,"offset":0.0},"rows":1,"cols":16},{"name":"TD Activation Thresholds (RPM)","address":788180,"type":"CURVE","dataType":"FLOAT32","unit":"Engine Speed (RPM)","factor":1.0,"offset":0.0,"rows":1,"cols":2},{"name":"TD Activation Thresholds (Target Boost) ","address":788160,"type":"CURVE","dataType":"FLOAT32","unit":"Target Boost (psi relative)","factor":0.01933677,"offset":0.0,"rows":1,"cols":2},{"name":"TD Integral Cumulative Range (WGDC Correction)","address":788188,"type":"CURVE","dataType":"FLOAT32","unit":"TD Integral Cumulative Wastegate Duty Correction (% absolute)","factor":1.0,"offset":0.0,"rows":1,"cols":2},{"name":"TD Integral Negative Activation (Boost Error)","address":788168,"type":"CURVE","dataType":"FLOAT32","unit":"Boost Error (psi)","factor":0.01933677,"offset":0.0,"rows":1,"cols":1},{"name":"TD Integral Positive Activation (Boost Error)","address":788172,"type":"CURVE","dataType":"FLOAT32","unit":"Boost Error (psi)","factor":0.01933677,"offset":0.0,"rows":1,"cols":1},{"name":"TD Integral Negative Activation (Wastegate Duty)","address":788176,"type":"CURVE","dataType":"FLOAT32","unit":"Wastegate Duty Cycle (%)","factor":1.0,"offset":0.0,"rows":1,"cols":1},{"name":"Manifold Pressure Sensor Scaling ","address":866572,"type":"CURVE","dataType":"FLOAT32","unit":"psi absolute","factor":0.01933677,"offset":0.0,"rows":1,"cols":2},{"name":"Manifold Pressure Sensor Limits (CEL)","address":866520,"type":"CURVE","dataType":"UWORD","unit":"Volts","factor":7.6293945e-05,"offset":0.0,"rows":1,"cols":2},{"name":"Manifold Pressure Sensor CEL Delays","address":801230,"type":"CURVE","dataType":"UBYTE","unit":"counter threshold","factor":1.0,"offset":0.0,"rows":1,"cols":2},{"name":"Primary Open Loop Fueling Base","address":830624,"type":"MAP","dataType":"UBYTE","unit":"Estimated Air/Fuel Ratio","factor":-0.1139534883720934,"offset":14.7,"xAxis":{"type":"COM_AXIS","points":16,"min":0,"max":0,"unit":"","address":830488,"dataType":"UWORD","factor":1.0,"offset":0.0},"yAxis":{"type":"COM_AXIS","points":18,"min":0,"max":0,"unit":"","address":830552,"dataType":"UWORD","factor":1.0,"offset":0.0},"rows":18,"cols":16},{"name":"Primary Open Loop Fueling Additive","address":831472,"type":"MAP","dataType":"UBYTE","unit":"'Primary Open Loop Fueling' Raw Enrichment Offset Additive","factor":0.0078125,"offset":0.0,"xAxis":{"type":"COM_AXIS","points":16,"min":0,"max":0,"unit":"","address":831336,"dataType":"UWORD","factor":1.0,"offset":0.0},"yAxis":{"type":"COM_AXIS","points":18,"min":0,"max":0,"unit":"","address":831400,"dataType":"UWORD","factor":1.0,"offset":0.0},"rows":18,"cols":16},{"name":"Minimum Active Primary Open Loop Enrichment","address":816004,"type":"CURVE","dataType":"FLOAT32","unit":"Estimated Air/Fuel Ratio","factor":-7.35,"offset":14.7,"rows":1,"cols":1},{"name":"Minimum Primary Open Loop Enrichment (Throttle)","address":818992,"type":"CURVE","dataType":"UBYTE","unit":"Estimated Primary Open Loop Air/Fuel Ratio Lean Limit","factor":-0.057198443579766334,"offset":14.7,"yAxis":{"type":"COM_AXIS","points":7,"min":0,"max":0,"unit":"","address":818964,"dataType":"UWORD","factor":1.0,"offset":0.0},"rows":1,"cols":7},{"name":"Minimum Primary Open Loop Enrichment (Accelerator)","address":819028,"type":"CURVE","dataType":"UBYTE","unit":"Estimated Primary Open Loop Air/Fuel Ratio Lean Limit","factor":-0.057198443579766334,"offset":14.7,"yAxis":{"type":"COM_AXIS","points":7,"min":0,"max":0,"unit":"","address":819000,"dataType":"UWORD","factor":1.0,"offset":0.0},"rows":1,"cols":7},{"name":"Primary Open Loop Fueling Compensation (ECT)","address":825432,"type":"CURVE","dataType":"UWORD","unit":"'Primary Open Loop Fueling' Enrichment Offset Compensation (%)","factor":0.003051757999998017,"offset":-100.0,"yAxis":{"type":"COM_AXIS","points":16,"min":0,"max":0,"unit":"","address":817072,"dataType":"UWORD","factor":1.0,"offset":0.0},"rows":1,"cols":16},{"name":"Front Oxygen Sensor Scaling","address":867712,"type":"CURVE","dataType":"FLOAT32","unit":"Air/Fuel Ratio","factor":14.7,"offset":0.0,"yAxis":{"type":"COM_AXIS","points":13,"min":0,"max":0,"unit":"","address":867660,"dataType":"UWORD","factor":1.0,"offset":0.0},"rows":1,"cols":13},{"name":"Front Oxygen Sensor Rich Limit","address":139404,"type":"CURVE","dataType":"FLOAT32","unit":"Air/Fuel Ratio","factor":14.7,"offset":0.0,"rows":1,"cols":1},{"name":"Front Oxygen Sensor Compensation (Atm. Pressure)","address":798204,"type":"CURVE","dataType":"UWORD","unit":"Front Oxygen Sensor Compensation","factor":3.051758e-05,"offset":0.0,"yAxis":{"type":"COM_AXIS","points":4,"min":0,"max":0,"unit":"","address":798188,"dataType":"UWORD","factor":1.0,"offset":0.0},"rows":1,"cols":4},{"name":"CL Fueling Target Compensation A (Load)","address":836940,"type":"MAP","dataType":"UWORD","unit":"Estimated Air/Fuel Ratio Points (Additive)","factor":0.000224304212999904,"offset":-7.35,"xAxis":{"type":"COM_AXIS","points":11,"min":0,"max":0,"unit":"","address":836852,"dataType":"UWORD","factor":1.0,"offset":0.0},"yAxis":{"type":"COM_AXIS","points":11,"min":0,"max":0,"unit":"","address":836896,"dataType":"UWORD","factor":1.0,"offset":0.0},"rows":11,"cols":11},{"name":"CL Fueling Target Compensation B (Load)","address":837604,"type":"MAP","dataType":"UWORD","unit":"Estimated Air/Fuel Ratio Points (Additive)","factor":0.000224304212999904,"offset":-7.35,"xAxis":{"type":"COM_AXIS","points":11,"min":0,"max":0,"unit":"","address":837516,"dataType":"UWORD","factor":1.0,"offset":0.0},"yAxis":{"type":"COM_AXIS","points":11,"min":0,"max":0,"unit":"","address":837560,"dataType":"UWORD","factor":1.0,"offset":0.0},"rows":11,"cols":11},{"name":"CL Fueling Target Compensation Imm. Cruise (ECT)","address":836316,"type":"MAP","dataType":"UWORD","unit":"Estimated Air/Fuel Ratio Points (Additive)","factor":-0.000224304212999904,"offset":7.350001,"xAxis":{"type":"COM_AXIS","points":16,"min":0,"max":0,"unit":"","address":817072,"dataType":"UWORD","factor":1.0,"offset":0.0},"yAxis":{"type":"COM_AXIS","points":3,"min":0,"max":0,"unit":"","address":836304,"dataType":"UWORD","factor":1.0,"offset":0.0},"rows":3,"cols":16},{"name":"CL Fueling Target Compensation Imm. Non-Cruise (ECT)","address":836424,"type":"MAP","dataType":"UWORD","unit":"Estimated Air/Fuel Ratio Points (Additive)","factor":-0.000224304212999904,"offset":7.350001,"xAxis":{"type":"COM_AXIS","points":16,"min":0,"max":0,"unit":"","address":817072,"dataType":"UWORD","factor":1.0,"offset":0.0},"yAxis":{"type":"COM_AXIS","points":3,"min":0,"max":0,"unit":"","address":836412,"dataType":"UWORD","factor":1.0,"offset":0.0},"rows":3,"cols":16},{"name":"CL to OL Delay","address":814730,"type":"CURVE","dataType":"UWORD","unit":"counter threshold","factor":1.0,"offset":0.0,"rows":1,"cols":2},{"name":"CL to OL Delay/Switch SI-DRIVE Intelligent","address":814728,"type":"CURVE","dataType":"UWORD","unit":"counter threshold","factor":1.0,"offset":0.0,"rows":1,"cols":1},{"name":"CL to OL Transition with Delay (Throttle)","address":818948,"type":"CURVE","dataType":"UBYTE","unit":"Throttle Plate Opening Angle (%)","factor":0.581287202,"offset":0.0,"yAxis":{"type":"COM_AXIS","points":16,"min":0,"max":0,"unit":"","address":818884,"dataType":"UWORD","factor":1.0,"offset":0.0},"rows":1,"cols":16},{"name":"CL to OL Transition with Delay Throttle Hysteresis","address":816012,"type":"CURVE","dataType":"FLOAT32","unit":"Throttle Plate Opening Angle (%)","factor":1.1904761904761905,"offset":0.0,"rows":1,"cols":1},{"name":"CL to OL Transition with Delay (Base Pulse Width)","address":825220,"type":"CURVE","dataType":"UWORD","unit":"Base Pulse Width (ms)","factor":0.004,"offset":0.0,"yAxis":{"type":"COM_AXIS","points":16,"min":0,"max":0,"unit":"","address":825156,"dataType":"UWORD","factor":1.0,"offset":0.0},"rows":1,"cols":16},{"name":"CL to OL Transition with Delay BPW Hysteresis","address":816008,"type":"CURVE","dataType":"FLOAT32","unit":"Base Pulse Width (ms)","factor":0.001,"offset":0.0,"rows":1,"cols":1},{"name":"CL to OL Transition Counter Step Value (MAF)","address":825292,"type":"CURVE","dataType":"UWORD","unit":"CL to OL Counter Increment (WARNING - value should NEVER be zero)","factor":1.0,"offset":0.0,"yAxis":{"type":"COM_AXIS","points":10,"min":0,"max":0,"unit":"","address":825252,"dataType":"UWORD","factor":1.0,"offset":0.0},"rows":1,"cols":10},{"name":"CL Delay Maximum (Vehicle Speed)","address":816136,"type":"CURVE","dataType":"FLOAT32","unit":"Vehicle Speed (MPH)","factor":0.621,"offset":0.0,"rows":1,"cols":2},{"name":"CL Delay Minimum (ECT)","address":816016,"type":"CURVE","dataType":"FLOAT32","unit":"Coolant Temp (Degrees F)","factor":1.7999999999999972,"offset":32.0,"rows":1,"cols":1},{"name":"CL Delay Maximum (Engine Load)","address":816152,"type":"CURVE","dataType":"FLOAT32","unit":"Engine Load (g/rev)","factor":1.0,"offset":0.0,"rows":1,"cols":2},{"name":"CL Delay Engine Load Counter Threshold","address":814726,"type":"CURVE","dataType":"UWORD","unit":"counter threshold","factor":1.0,"offset":0.0,"rows":1,"cols":1},{"name":"CL Delay Maximum Engine Speed (Per Gear)","address":816068,"type":"CURVE","dataType":"FLOAT32","unit":"Engine Speed (RPM)","factor":1.0,"offset":0.0,"rows":1,"cols":10},{"name":"CL Delay Maximum Engine Speed (Neutral)","address":816060,"type":"CURVE","dataType":"FLOAT32","unit":"Engine Speed (RPM)","factor":1.0,"offset":0.0,"rows":1,"cols":2},{"name":"CL Delay Throttle Atm. Pressure Thresholds","address":816112,"type":"CURVE","dataType":"FLOAT32","unit":"Atmospheric Pressure (psi)","factor":0.01933677,"offset":0.0,"rows":1,"cols":2},{"name":"CL Delay Maximum (Throttle) (Low Atm. Pressure)","address":816120,"type":"CURVE","dataType":"FLOAT32","unit":"Throttle Plate Opening Angle (%)","factor":1.1904761904761905,"offset":0.0,"rows":1,"cols":2},{"name":"CL Delay Maximum (Throttle) (High Atm. Pressure)","address":816128,"type":"CURVE","dataType":"FLOAT32","unit":"Throttle Plate Opening Angle (%)","factor":1.1904761904761905,"offset":0.0,"rows":1,"cols":2},{"name":"Injector Latency ","address":835336,"type":"MAP","dataType":"UWORD","unit":"Latency (ms)","factor":0.00025,"offset":0.0,"xAxis":{"type":"COM_AXIS","points":5,"min":0,"max":0,"unit":"","address":835304,"dataType":"UWORD","factor":1.0,"offset":0.0},"yAxis":{"type":"COM_AXIS","points":3,"min":0,"max":0,"unit":"","address":835324,"dataType":"UWORD","factor":1.0,"offset":0.0},"rows":3,"cols":5},{"name":"Injector Flow Scaling","address":815188,"type":"CURVE","dataType":"FLOAT32","unit":"ESTIMATED Flow Rate - Gas Only (cc/min)","factor":-1353545.0,"offset":4060635.0,"rows":1,"cols":1},{"name":"Per Injector Pulse Width Compensation A","address":833212,"type":"MAP","dataType":"UBYTE","unit":"Injector Pulse Width Compensation","factor":0.78125,"offset":-100.0,"xAxis":{"type":"COM_AXIS","points":17,"min":0,"max":0,"unit":"","address":833076,"dataType":"UWORD","factor":1.0,"offset":0.0},"yAxis":{"type":"COM_AXIS","points":17,"min":0,"max":0,"unit":"","address":833144,"dataType":"UWORD","factor":1.0,"offset":0.0},"rows":17,"cols":17},{"name":"Per Injector Pulse Width Compensation B","address":833640,"type":"MAP","dataType":"UBYTE","unit":"Injector Pulse Width Compensation","factor":0.78125,"offset":-100.0,"xAxis":{"type":"COM_AXIS","points":17,"min":0,"max":0,"unit":"","address":833504,"dataType":"UWORD","factor":1.0,"offset":0.0},"yAxis":{"type":"COM_AXIS","points":17,"min":0,"max":0,"unit":"","address":833572,"dataType":"UWORD","factor":1.0,"offset":0.0},"rows":17,"cols":17},{"name":"Per Injector Pulse Width Compensation C","address":834068,"type":"MAP","dataType":"UBYTE","unit":"Injector Pulse Width Compensation","factor":0.78125,"offset":-100.0,"xAxis":{"type":"COM_AXIS","points":17,"min":0,"max":0,"unit":"","address":833932,"dataType":"UWORD","factor":1.0,"offset":0.0},"yAxis":{"type":"COM_AXIS","points":17,"min":0,"max":0,"unit":"","address":834000,"dataType":"UWORD","factor":1.0,"offset":0.0},"rows":17,"cols":17},{"name":"Per Injector Pulse Width Compensation D","address":834496,"type":"MAP","dataType":"UBYTE","unit":"Injector Pulse Width Compensation","factor":0.78125,"offset":-100.0,"xAxis":{"type":"COM_AXIS","points":17,"min":0,"max":0,"unit":"","address":834360,"dataType":"UWORD","factor":1.0,"offset":0.0},"yAxis":{"type":"COM_AXIS","points":17,"min":0,"max":0,"unit":"","address":834428,"dataType":"UWORD","factor":1.0,"offset":0.0},"rows":17,"cols":17},{"name":"Cranking Fuel Injector Pulse Width A (ECT)","address":820346,"type":"CURVE","dataType":"UWORD","unit":"Injector Pulse Width (ms)","factor":0.008,"offset":0.0,"yAxis":{"type":"COM_AXIS","points":16,"min":0,"max":0,"unit":"","address":817072,"dataType":"UWORD","factor":1.0,"offset":0.0},"rows":1,"cols":16},{"name":"Cranking Fuel Injector Pulse Width B (ECT)","address":820378,"type":"CURVE","dataType":"UWORD","unit":"Injector Pulse Width (ms)","factor":0.008,"offset":0.0,"yAxis":{"type":"COM_AXIS","points":16,"min":0,"max":0,"unit":"","address":817072,"dataType":"UWORD","factor":1.0,"offset":0.0},"rows":1,"cols":16},{"name":"Cranking Fuel Injector Pulse Width C (ECT)","address":820410,"type":"CURVE","dataType":"UWORD","unit":"Injector Pulse Width (ms)","factor":0.008,"offset":0.0,"yAxis":{"type":"COM_AXIS","points":16,"min":0,"max":0,"unit":"","address":817072,"dataType":"UWORD","factor":1.0,"offset":0.0},"rows":1,"cols":16},{"name":"Cranking Fuel Injector Pulse Width D (ECT)","address":820442,"type":"CURVE","dataType":"UWORD","unit":"Injector Pulse Width (ms)","factor":0.008,"offset":0.0,"yAxis":{"type":"COM_AXIS","points":16,"min":0,"max":0,"unit":"","address":817072,"dataType":"UWORD","factor":1.0,"offset":0.0},"rows":1,"cols":16},{"name":"Cranking Fuel Injector Pulse Width E (ECT)","address":820474,"type":"CURVE","dataType":"UWORD","unit":"Injector Pulse Width (ms)","factor":0.008,"offset":0.0,"yAxis":{"type":"COM_AXIS","points":16,"min":0,"max":0,"unit":"","address":817072,"dataType":"UWORD","factor":1.0,"offset":0.0},"rows":1,"cols":16},{"name":"Cranking Fuel Injector Pulse Width F (ECT)","address":820506,"type":"CURVE","dataType":"UWORD","unit":"Injector Pulse Width (ms)","factor":0.008,"offset":0.0,"yAxis":{"type":"COM_AXIS","points":16,"min":0,"max":0,"unit":"","address":817072,"dataType":"UWORD","factor":1.0,"offset":0.0},"rows":1,"cols":16},{"name":"Cranking Fuel IPW Compensation Imm. Cruise (RPM)","address":828888,"type":"MAP","dataType":"UBYTE","unit":"Cranking Fuel Injector Pulse Width Compensation (%)","factor":0.78125,"offset":-100.0,"xAxis":{"type":"COM_AXIS","points":5,"min":0,"max":0,"unit":"","address":828840,"dataType":"UWORD","factor":1.0,"offset":0.0},"yAxis":{"type":"COM_AXIS","points":7,"min":0,"max":0,"unit":"","address":828860,"dataType":"UWORD","factor":1.0,"offset":0.0},"rows":7,"cols":5},{"name":"Cranking Fuel IPW Compensation Imm. Non-Cruise (RPM)","address":828804,"type":"MAP","dataType":"UBYTE","unit":"Cranking Fuel Injector Pulse Width Compensation (%)","factor":0.78125,"offset":-100.0,"xAxis":{"type":"COM_AXIS","points":5,"min":0,"max":0,"unit":"","address":828756,"dataType":"UWORD","factor":1.0,"offset":0.0},"yAxis":{"type":"COM_AXIS","points":7,"min":0,"max":0,"unit":"","address":828776,"dataType":"UWORD","factor":1.0,"offset":0.0},"rows":7,"cols":5},{"name":"Cranking Fuel IPW Compensation (MAP)","address":817652,"type":"CURVE","dataType":"UBYTE","unit":"Cranking Fuel Injector Pulse Width Compensation (%)","factor":0.78125,"offset":-100.0,"yAxis":{"type":"COM_AXIS","points":10,"min":0,"max":0,"unit":"","address":817612,"dataType":"UWORD","factor":1.0,"offset":0.0},"rows":1,"cols":10},{"name":"Cranking Fuel IPW Compensation (Accelerator)","address":817704,"type":"CURVE","dataType":"UBYTE","unit":"Cranking Fuel Injector Pulse Width Compensation (%)","factor":0.78125,"offset":-100.0,"yAxis":{"type":"COM_AXIS","points":10,"min":0,"max":0,"unit":"","address":817664,"dataType":"UWORD","factor":1.0,"offset":0.0},"rows":1,"cols":10},{"name":"Cranking Fuel IPW Compensation (IAT)","address":817736,"type":"CURVE","dataType":"UBYTE","unit":"Cranking Fuel Injector Pulse Width Compensation (%)","factor":0.78125,"offset":-100.0,"yAxis":{"type":"COM_AXIS","points":5,"min":0,"max":0,"unit":"","address":817716,"dataType":"UWORD","factor":1.0,"offset":0.0},"rows":1,"cols":5},{"name":"Throttle Tip-in Enrichment A","address":826588,"type":"CURVE","dataType":"UWORD","unit":"Additional Injector Pulse Width (ms)","factor":0.004,"offset":0.0,"yAxis":{"type":"COM_AXIS","points":18,"min":0,"max":0,"unit":"","address":826516,"dataType":"UWORD","factor":1.0,"offset":0.0},"rows":1,"cols":18},{"name":"Throttle Tip-in Enrichment B","address":826696,"type":"CURVE","dataType":"UWORD","unit":"Additional Injector Pulse Width (ms)","factor":0.004,"offset":0.0,"yAxis":{"type":"COM_AXIS","points":18,"min":0,"max":0,"unit":"","address":826624,"dataType":"UWORD","factor":1.0,"offset":0.0},"rows":1,"cols":18},{"name":"Minimum Tip-in Enrichment Activation","address":816808,"type":"CURVE","dataType":"FLOAT32","unit":"Additional Injector Pulse Width (ms)","factor":0.004,"offset":0.0,"rows":1,"cols":1},{"name":"Minimum Tip-in Enrichment Activation (Throttle)","address":816804,"type":"CURVE","dataType":"FLOAT32","unit":"Throttle Angle Change (%)","factor":1.0,"offset":0.0,"rows":1,"cols":1},{"name":"Tip-in Enrichment Compensation (Boost Error)","address":819936,"type":"CURVE","dataType":"UBYTE","unit":"Throttle Tip-in Enrichment Compensation (%)","factor":0.78125,"offset":-100.0,"yAxis":{"type":"COM_AXIS","points":9,"min":0,"max":0,"unit":"","address":819900,"dataType":"UWORD","factor":1.0,"offset":0.0},"rows":1,"cols":9},{"name":"Tip-in Enrichment Compensation (RPM)","address":819884,"type":"CURVE","dataType":"UBYTE","unit":"Throttle Tip-in Enrichment Compensation (%)","factor":0.78125,"offset":-100.0,"yAxis":{"type":"COM_AXIS","points":16,"min":0,"max":0,"unit":"","address":819820,"dataType":"UWORD","factor":1.0,"offset":0.0},"rows":1,"cols":16},{"name":"Tip-in Enrichment Compensation A (ECT)","address":819945,"type":"CURVE","dataType":"UBYTE","unit":"Throttle Tip-in Enrichment Compensation (%)","factor":0.78125,"offset":-100.0,"yAxis":{"type":"COM_AXIS","points":16,"min":0,"max":0,"unit":"","address":817072,"dataType":"UWORD","factor":1.0,"offset":0.0},"rows":1,"cols":16},{"name":"Tip-in Enrichment Compensation B (ECT)","address":826732,"type":"CURVE","dataType":"UWORD","unit":"Throttle Tip-in Enrichment Compensation (%)","factor":0.01220703125,"offset":-100.0,"yAxis":{"type":"COM_AXIS","points":16,"min":0,"max":0,"unit":"","address":817072,"dataType":"UWORD","factor":1.0,"offset":0.0},"rows":1,"cols":16},{"name":"Tip-in Enrichment Compensation C (ECT)","address":826764,"type":"CURVE","dataType":"UWORD","unit":"Throttle Tip-in Enrichment Compensation (%)","factor":0.01220703125,"offset":-100.0,"yAxis":{"type":"COM_AXIS","points":16,"min":0,"max":0,"unit":"","address":817072,"dataType":"UWORD","factor":1.0,"offset":0.0},"rows":1,"cols":16},{"name":"Tip-in Enrichment Compensation D (ECT)","address":826828,"type":"CURVE","dataType":"UWORD","unit":"Throttle Tip-in Enrichment Compensation (%)","factor":0.048828119999996034,"offset":-99.99998976,"yAxis":{"type":"COM_AXIS","points":16,"min":0,"max":0,"unit":"","address":817136,"dataType":"UWORD","factor":1.0,"offset":0.0},"rows":1,"cols":16},{"name":"Tip-in Enrichment Compensation D (ECT) Activation","address":816812,"type":"CURVE","dataType":"FLOAT32","unit":"Throttle Angle Change (%)","factor":1.0,"offset":0.0,"rows":1,"cols":1},{"name":"Tip-in Enrichment Disable Applied Counter Threshold A (ECT)","address":819961,"type":"CURVE","dataType":"UBYTE","unit":"tip-in enrichment applied counter","factor":1.0,"offset":0.0,"yAxis":{"type":"COM_AXIS","points":16,"min":0,"max":0,"unit":"","address":817072,"dataType":"UWORD","factor":1.0,"offset":0.0},"rows":1,"cols":16},{"name":"Tip-in Enrichment Disable Applied Counter Threshold B (ECT)","address":819977,"type":"CURVE","dataType":"UBYTE","unit":"tip-in enrichment applied counter","factor":1.0,"offset":0.0,"yAxis":{"type":"COM_AXIS","points":16,"min":0,"max":0,"unit":"","address":817072,"dataType":"UWORD","factor":1.0,"offset":0.0},"rows":1,"cols":16},{"name":"Tip-in Enrichment Applied Counter Reset","address":814649,"type":"CURVE","dataType":"UBYTE","unit":"tip-in last applied counter period","factor":1.0,"offset":0.0,"rows":1,"cols":1},{"name":"Tip-in Enrichment Disable Throttle Cumulative Threshold A (ECT)","address":826860,"type":"CURVE","dataType":"UWORD","unit":"cumulative throttle angle change","factor":0.001907349,"offset":0.0,"yAxis":{"type":"COM_AXIS","points":16,"min":0,"max":0,"unit":"","address":817072,"dataType":"UWORD","factor":1.0,"offset":0.0},"rows":1,"cols":16},{"name":"Tip-in Enrichment Disable Throttle Cumulative Threshold B (ECT)","address":826892,"type":"CURVE","dataType":"UWORD","unit":"cumulative throttle angle change","factor":0.001907349,"offset":0.0,"yAxis":{"type":"COM_AXIS","points":16,"min":0,"max":0,"unit":"","address":817072,"dataType":"UWORD","factor":1.0,"offset":0.0},"rows":1,"cols":16},{"name":"Tip-in Throttle Cumulative Reset","address":814650,"type":"CURVE","dataType":"UBYTE","unit":"tip-in last applied counter period","factor":1.0,"offset":0.0,"rows":1,"cols":1},{"name":"Min Primary Base Enrichment 1 Cruise","address":829620,"type":"MAP","dataType":"UBYTE","unit":"Minimum Primary Enrichment Offset Additive Cruise","factor":0.00390625,"offset":0.0,"xAxis":{"type":"COM_AXIS","points":16,"min":0,"max":0,"unit":"","address":817072,"dataType":"UWORD","factor":1.0,"offset":0.0},"yAxis":{"type":"COM_AXIS","points":8,"min":0,"max":0,"unit":"","address":829588,"dataType":"UWORD","factor":1.0,"offset":0.0},"rows":8,"cols":16},{"name":"Min Primary Base Enrichment 1 Non-Cruise","address":829460,"type":"MAP","dataType":"UBYTE","unit":"Minimum Primary Enrichment Offset Additive Non-Cruise","factor":0.00390625,"offset":0.0,"xAxis":{"type":"COM_AXIS","points":16,"min":0,"max":0,"unit":"","address":817072,"dataType":"UWORD","factor":1.0,"offset":0.0},"yAxis":{"type":"COM_AXIS","points":8,"min":0,"max":0,"unit":"","address":829428,"dataType":"UWORD","factor":1.0,"offset":0.0},"rows":8,"cols":16},{"name":"Min Primary Base Enrichment 1 (Non-Primary OL) ","address":817837,"type":"CURVE","dataType":"UBYTE","unit":"Minimum Primary Enrichment Offset Additive 1","factor":0.00390625,"offset":0.0,"yAxis":{"type":"COM_AXIS","points":16,"min":0,"max":0,"unit":"","address":817072,"dataType":"UWORD","factor":1.0,"offset":0.0},"rows":1,"cols":16},{"name":"A/F Learning #1 Limits","address":815744,"type":"CURVE","dataType":"FLOAT32","unit":"A/F Learning #1 Limits (%)","factor":100.0,"offset":0.0,"rows":1,"cols":2},{"name":"A/F Learning #1 Airflow Ranges","address":815760,"type":"CURVE","dataType":"FLOAT32","unit":"Mass Airflow (g/s)","factor":1.0,"offset":0.0,"rows":1,"cols":3},{"name":"MAF Limit (Maximum)","address":797024,"type":"CURVE","dataType":"FLOAT32","unit":"Mass Airflow (g/s)","factor":1.0,"offset":0.0,"rows":1,"cols":1},{"name":"MAF Sensor Scaling","address":867444,"type":"CURVE","dataType":"FLOAT32","unit":"Mass Airflow (g/s)","factor":1.0,"offset":0.0,"yAxis":{"type":"COM_AXIS","points":54,"min":0,"max":0,"unit":"","address":867228,"dataType":"UWORD","factor":1.0,"offset":0.0},"rows":1,"cols":54},{"name":"MAF Compensation (IAT)","address":798928,"type":"MAP","dataType":"UBYTE","unit":"Mass Airflow Compensation (%)","factor":0.390625,"offset":-50.0,"xAxis":{"type":"COM_AXIS","points":5,"min":0,"max":0,"unit":"","address":798876,"dataType":"UWORD","factor":1.0,"offset":0.0},"yAxis":{"type":"COM_AXIS","points":8,"min":0,"max":0,"unit":"","address":798896,"dataType":"UWORD","factor":1.0,"offset":0.0},"rows":8,"cols":5},{"name":"Engine Load Limit A (Maximum)","address":133432,"type":"CURVE","dataType":"FLOAT32","unit":"Engine Load (g/rev)","factor":1.0,"offset":0.0,"rows":1,"cols":1},{"name":"Engine Load Limit B Maximum (RPM)","address":797948,"type":"CURVE","dataType":"UWORD","unit":"Engine Load (g/rev)","factor":6.103516e-05,"offset":0.0,"yAxis":{"type":"COM_AXIS","points":2,"min":0,"max":0,"unit":"","address":797940,"dataType":"UWORD","factor":1.0,"offset":0.0},"rows":1,"cols":2},{"name":"Engine Load Compensation Cruise (MP)","address":799072,"type":"MAP","dataType":"UBYTE","unit":"Engine Load Compensation (%)","factor":0.390625,"offset":-50.0,"xAxis":{"type":"COM_AXIS","points":12,"min":0,"max":0,"unit":"","address":798968,"dataType":"UWORD","factor":1.0,"offset":0.0},"yAxis":{"type":"COM_AXIS","points":14,"min":0,"max":0,"unit":"","address":799016,"dataType":"UWORD","factor":1.0,"offset":0.0},"rows":14,"cols":12},{"name":"Engine Load Compensation Non-Cruise (MP)","address":799344,"type":"MAP","dataType":"UBYTE","unit":"Engine Load Compensation (%)","factor":0.390625,"offset":-50.0,"xAxis":{"type":"COM_AXIS","points":12,"min":0,"max":0,"unit":"","address":799240,"dataType":"UWORD","factor":1.0,"offset":0.0},"yAxis":{"type":"COM_AXIS","points":14,"min":0,"max":0,"unit":"","address":799288,"dataType":"UWORD","factor":1.0,"offset":0.0},"rows":14,"cols":12},{"name":"Base Timing Primary Cruise","address":850468,"type":"MAP","dataType":"UBYTE","unit":"Base Ignition Timing (degrees BTDC)","factor":0.3515625,"offset":-20.0,"xAxis":{"type":"COM_AXIS","points":22,"min":0,"max":0,"unit":"","address":850308,"dataType":"UWORD","factor":1.0,"offset":0.0},"yAxis":{"type":"COM_AXIS","points":18,"min":0,"max":0,"unit":"","address":850396,"dataType":"UWORD","factor":1.0,"offset":0.0},"rows":18,"cols":22},{"name":"Base Timing Reference Cruise (AVCS related)","address":851580,"type":"MAP","dataType":"UBYTE","unit":"Base Ignition Timing (degrees BTDC)","factor":0.3515625,"offset":-20.0,"xAxis":{"type":"COM_AXIS","points":22,"min":0,"max":0,"unit":"","address":851420,"dataType":"UWORD","factor":1.0,"offset":0.0},"yAxis":{"type":"COM_AXIS","points":18,"min":0,"max":0,"unit":"","address":851508,"dataType":"UWORD","factor":1.0,"offset":0.0},"rows":18,"cols":22},{"name":"Base Timing Primary Non-Cruise","address":851024,"type":"MAP","dataType":"UBYTE","unit":"Base Ignition Timing (degrees BTDC)","factor":0.3515625,"offset":-20.0,"xAxis":{"type":"COM_AXIS","points":22,"min":0,"max":0,"unit":"","address":850864,"dataType":"UWORD","factor":1.0,"offset":0.0},"yAxis":{"type":"COM_AXIS","points":18,"min":0,"max":0,"unit":"","address":850952,"dataType":"UWORD","factor":1.0,"offset":0.0},"rows":18,"cols":22},{"name":"Base Timing Reference Non-Cruise (AVCS related)","address":852136,"type":"MAP","dataType":"UBYTE","unit":"Base Ignition Timing (degrees BTDC)","factor":0.3515625,"offset":-20.0,"xAxis":{"type":"COM_AXIS","points":22,"min":0,"max":0,"unit":"","address":851976,"dataType":"UWORD","factor":1.0,"offset":0.0},"yAxis":{"type":"COM_AXIS","points":18,"min":0,"max":0,"unit":"","address":852064,"dataType":"UWORD","factor":1.0,"offset":0.0},"rows":18,"cols":22},{"name":"Base Timing Idle A (In-Gear)","address":843570,"type":"CURVE","dataType":"UBYTE","unit":"Base Ignition Timing (degrees BTDC)","factor":0.3515625,"offset":-20.0,"yAxis":{"type":"COM_AXIS","points":16,"min":0,"max":0,"unit":"","address":842972,"dataType":"UWORD","factor":1.0,"offset":0.0},"rows":1,"cols":16},{"name":"Base Timing Idle B (In-Gear)","address":843586,"type":"CURVE","dataType":"UBYTE","unit":"Base Ignition Timing (degrees BTDC)","factor":0.3515625,"offset":-20.0,"yAxis":{"type":"COM_AXIS","points":16,"min":0,"max":0,"unit":"","address":842972,"dataType":"UWORD","factor":1.0,"offset":0.0},"rows":1,"cols":16},{"name":"Base Timing Idle A (Neutral)","address":843602,"type":"CURVE","dataType":"UBYTE","unit":"Base Ignition Timing (degrees BTDC)","factor":0.3515625,"offset":-20.0,"yAxis":{"type":"COM_AXIS","points":16,"min":0,"max":0,"unit":"","address":842972,"dataType":"UWORD","factor":1.0,"offset":0.0},"rows":1,"cols":16},{"name":"Base Timing Idle B (Neutral)","address":843618,"type":"CURVE","dataType":"UBYTE","unit":"Base Ignition Timing (degrees BTDC)","factor":0.3515625,"offset":-20.0,"yAxis":{"type":"COM_AXIS","points":16,"min":0,"max":0,"unit":"","address":842972,"dataType":"UWORD","factor":1.0,"offset":0.0},"rows":1,"cols":16},{"name":"Base Timing Idle Minimum","address":843561,"type":"CURVE","dataType":"UBYTE","unit":"Base Ignition Timing (degrees BTDC)","factor":0.3515625,"offset":-20.0,"yAxis":{"type":"COM_AXIS","points":9,"min":0,"max":0,"unit":"","address":843100,"dataType":"UWORD","factor":1.0,"offset":0.0},"rows":1,"cols":9},{"name":"Base Timing Idle Minimum Vehicle Speed Enable","address":842456,"type":"CURVE","dataType":"FLOAT32","unit":"Vehicle Speed (MPH)","factor":0.621,"offset":0.0,"rows":1,"cols":1},{"name":"Knock Correction Advance Max Cruise","address":849240,"type":"MAP","dataType":"UBYTE","unit":"Maximum Knock Correction Timing Advance (degrees)","factor":0.3515625,"offset":0.0,"xAxis":{"type":"COM_AXIS","points":22,"min":0,"max":0,"unit":"","address":849080,"dataType":"UWORD","factor":1.0,"offset":0.0},"yAxis":{"type":"COM_AXIS","points":18,"min":0,"max":0,"unit":"","address":849168,"dataType":"UWORD","factor":1.0,"offset":0.0},"rows":18,"cols":22},{"name":"Knock Correction Advance Max Non-Cruise","address":849796,"type":"MAP","dataType":"UBYTE","unit":"Maximum Knock Correction Timing Advance (degrees)","factor":0.3515625,"offset":0.0,"xAxis":{"type":"COM_AXIS","points":22,"min":0,"max":0,"unit":"","address":849636,"dataType":"UWORD","factor":1.0,"offset":0.0},"yAxis":{"type":"COM_AXIS","points":18,"min":0,"max":0,"unit":"","address":849724,"dataType":"UWORD","factor":1.0,"offset":0.0},"rows":18,"cols":22},{"name":"Timing Compensation A (IAT)","address":843796,"type":"CURVE","dataType":"UBYTE","unit":"Ignition Timing Correction (degrees)","factor":0.3515625,"offset":-45.0,"yAxis":{"type":"COM_AXIS","points":16,"min":0,"max":0,"unit":"","address":843732,"dataType":"UWORD","factor":1.0,"offset":0.0},"rows":1,"cols":16},{"name":"Timing Compensation A (IAT) Activation","address":852596,"type":"MAP","dataType":"UBYTE","unit":"Timing Compensation Intake Temp Map Target Compensation (%)","factor":0.78125,"offset":-100.0,"xAxis":{"type":"COM_AXIS","points":8,"min":0,"max":0,"unit":"","address":852532,"dataType":"UWORD","factor":1.0,"offset":0.0},"yAxis":{"type":"COM_AXIS","points":8,"min":0,"max":0,"unit":"","address":852564,"dataType":"UWORD","factor":1.0,"offset":0.0},"rows":8,"cols":8},{"name":"Timing Compensation B (IAT)","address":845468,"type":"CURVE","dataType":"UBYTE","unit":"Ignition Timing Correction (degrees)","factor":0.3515625,"offset":-45.0,"yAxis":{"type":"COM_AXIS","points":16,"min":0,"max":0,"unit":"","address":845404,"dataType":"UWORD","factor":1.0,"offset":0.0},"rows":1,"cols":16},{"name":"Timing Compensation B (IAT) IAM Activation","address":842884,"type":"CURVE","dataType":"FLOAT32","unit":"Ignition Advance Multiplier (IAM)","factor":1.0,"offset":0.0,"rows":1,"cols":1},{"name":"Timing Compensation B (IAT) Max Additive","address":842856,"type":"CURVE","dataType":"FLOAT32","unit":"degrees of correction","factor":1.0,"offset":0.0,"rows":1,"cols":1},{"name":"Timing Compensation Imm. Cruise A (ECT)","address":843698,"type":"CURVE","dataType":"UBYTE","unit":"Ignition Timing Correction (degrees)","factor":0.3515625,"offset":-45.0,"yAxis":{"type":"COM_AXIS","points":16,"min":0,"max":0,"unit":"","address":842972,"dataType":"UWORD","factor":1.0,"offset":0.0},"rows":1,"cols":16},{"name":"Timing Compensation Imm. Cruise B (ECT)","address":843714,"type":"CURVE","dataType":"UBYTE","unit":"Ignition Timing Correction (degrees)","factor":0.3515625,"offset":-45.0,"yAxis":{"type":"COM_AXIS","points":16,"min":0,"max":0,"unit":"","address":842972,"dataType":"UWORD","factor":1.0,"offset":0.0},"rows":1,"cols":16},{"name":"Timing Compensation Imm. Non-Cruise A (ECT)","address":843666,"type":"CURVE","dataType":"UBYTE","unit":"Ignition Timing Correction (degrees)","factor":0.3515625,"offset":-45.0,"yAxis":{"type":"COM_AXIS","points":16,"min":0,"max":0,"unit":"","address":842972,"dataType":"UWORD","factor":1.0,"offset":0.0},"rows":1,"cols":16},{"name":"Timing Compensation Imm. Non-Cruise B (ECT)","address":843682,"type":"CURVE","dataType":"UBYTE","unit":"Ignition Timing Correction (degrees)","factor":0.3515625,"offset":-45.0,"yAxis":{"type":"COM_AXIS","points":16,"min":0,"max":0,"unit":"","address":842972,"dataType":"UWORD","factor":1.0,"offset":0.0},"rows":1,"cols":16},{"name":"Timing Compensation Per Cylinder A","address":848568,"type":"MAP","dataType":"UBYTE","unit":"Ignition Timing Correction (degrees)","factor":0.3515625,"offset":-45.0,"xAxis":{"type":"COM_AXIS","points":14,"min":0,"max":0,"unit":"","address":848496,"dataType":"UWORD","factor":1.0,"offset":0.0},"yAxis":{"type":"COM_AXIS","points":4,"min":0,"max":0,"unit":"","address":848552,"dataType":"UWORD","factor":1.0,"offset":0.0},"rows":4,"cols":14},{"name":"Timing Compensation Per Cylinder B","address":848696,"type":"MAP","dataType":"UBYTE","unit":"Ignition Timing Correction (degrees)","factor":0.3515625,"offset":-45.0,"xAxis":{"type":"COM_AXIS","points":14,"min":0,"max":0,"unit":"","address":848624,"dataType":"UWORD","factor":1.0,"offset":0.0},"yAxis":{"type":"COM_AXIS","points":4,"min":0,"max":0,"unit":"","address":848680,"dataType":"UWORD","factor":1.0,"offset":0.0},"rows":4,"cols":14},{"name":"Timing Compensation Per Cylinder C","address":848824,"type":"MAP","dataType":"UBYTE","unit":"Ignition Timing Correction (degrees)","factor":0.3515625,"offset":-45.0,"xAxis":{"type":"COM_AXIS","points":14,"min":0,"max":0,"unit":"","address":848752,"dataType":"UWORD","factor":1.0,"offset":0.0},"yAxis":{"type":"COM_AXIS","points":4,"min":0,"max":0,"unit":"","address":848808,"dataType":"UWORD","factor":1.0,"offset":0.0},"rows":4,"cols":14},{"name":"Timing Compensation Per Cylinder D","address":848956,"type":"MAP","dataType":"UBYTE","unit":"Ignition Timing Correction (degrees)","factor":0.3515625,"offset":-45.0,"xAxis":{"type":"COM_AXIS","points":14,"min":0,"max":0,"unit":"","address":848880,"dataType":"UWORD","factor":1.0,"offset":0.0},"yAxis":{"type":"COM_AXIS","points":5,"min":0,"max":0,"unit":"","address":848936,"dataType":"UWORD","factor":1.0,"offset":0.0},"rows":5,"cols":14},{"name":"Timing Comp Minimum Load (Per Cylinder)","address":841720,"type":"CURVE","dataType":"FLOAT32","unit":"Engine Load (g/rev)","factor":1.0,"offset":0.0,"rows":1,"cols":1},{"name":"Timing Comp Maximum RPM (Per Cylinder)","address":841716,"type":"CURVE","dataType":"FLOAT32","unit":"Engine Speed (RPM)","factor":1.0,"offset":0.0,"rows":1,"cols":1},{"name":"Timing Comp Minimum Coolant Temp (Per Cylinder)","address":841724,"type":"CURVE","dataType":"FLOAT32","unit":"Coolant Temp (Degrees F)","factor":1.7999999999999972,"offset":32.0,"rows":1,"cols":1},{"name":"Feedback Correction Range (RPM)","address":841736,"type":"CURVE","dataType":"FLOAT32","unit":"Engine Speed (RPM)","factor":1.0,"offset":0.0,"rows":1,"cols":4},{"name":"Feedback Correction Minimum Load","address":841728,"type":"CURVE","dataType":"FLOAT32","unit":"Engine Load (g/rev)","factor":1.0,"offset":0.0,"rows":1,"cols":2},{"name":"Feedback Correction Retard Value","address":841768,"type":"CURVE","dataType":"FLOAT32","unit":"degrees of correction","factor":-1.0,"offset":0.0,"rows":1,"cols":1},{"name":"Feedback Correction Retard Limit","address":841764,"type":"CURVE","dataType":"FLOAT32","unit":"degrees of correction","factor":-1.0,"offset":0.0,"rows":1,"cols":1},{"name":"Feedback Correction Negative Advance Value","address":841772,"type":"CURVE","dataType":"FLOAT32","unit":"degrees of correction","factor":1.0,"offset":0.0,"rows":1,"cols":1},{"name":"Feedback Correction Negative Advance Delay","address":841576,"type":"CURVE","dataType":"UWORD","unit":"counter threshold","factor":1.0,"offset":0.0,"rows":1,"cols":1},{"name":"Extended Feedback Correction High RPM Compensation","address":841780,"type":"CURVE","dataType":"FLOAT32","unit":"multiplier","factor":1.0,"offset":0.0,"rows":1,"cols":1},{"name":"Fine Correction Range (RPM)","address":842192,"type":"CURVE","dataType":"FLOAT32","unit":"Engine Speed (RPM)","factor":1.0,"offset":0.0,"rows":1,"cols":4},{"name":"Fine Correction Range (Load)","address":842208,"type":"CURVE","dataType":"FLOAT32","unit":"Engine Load (g/rev)","factor":1.0,"offset":0.0,"rows":1,"cols":4},{"name":"Fine Correction Rows (RPM)","address":842096,"type":"CURVE","dataType":"FLOAT32","unit":"Engine Speed (RPM)","factor":1.0,"offset":0.0,"rows":1,"cols":6},{"name":"Fine Correction Columns (Load)","address":842124,"type":"CURVE","dataType":"FLOAT32","unit":"Engine Load (g/rev)","factor":1.0,"offset":0.0,"rows":1,"cols":4},{"name":"Fine Correction Retard Value A","address":842164,"type":"CURVE","dataType":"FLOAT32","unit":"degrees of correction","factor":-1.0,"offset":0.0,"rows":1,"cols":1},{"name":"Fine Correction Retard Value B","address":842184,"type":"CURVE","dataType":"FLOAT32","unit":"degrees of correction","factor":-1.0,"offset":0.0,"rows":1,"cols":1},{"name":"Fine Correction Retard Limit","address":842160,"type":"CURVE","dataType":"FLOAT32","unit":"degrees of correction","factor":1.0,"offset":0.0,"rows":1,"cols":1},{"name":"Fine Correction Advance Value","address":842156,"type":"CURVE","dataType":"FLOAT32","unit":"degrees of correction","factor":1.0,"offset":0.0,"rows":1,"cols":1},{"name":"Fine Correction Advance Limit","address":842152,"type":"CURVE","dataType":"FLOAT32","unit":"degrees of correction","factor":1.0,"offset":0.0,"rows":1,"cols":1},{"name":"Fine Correction Advance Delay","address":841592,"type":"CURVE","dataType":"UWORD","unit":"counter threshold","factor":1.0,"offset":0.0,"rows":1,"cols":1},{"name":"Rough Correction Range (RPM)","address":842008,"type":"CURVE","dataType":"FLOAT32","unit":"Engine Speed (RPM)","factor":1.0,"offset":0.0,"rows":1,"cols":4},{"name":"Rough Correction Range (Load)","address":842024,"type":"CURVE","dataType":"FLOAT32","unit":"Engine Load (g/rev)","factor":1.0,"offset":0.0,"rows":1,"cols":4},{"name":"Rough Correction Minimum KC Advance Map Value","address":842040,"type":"CURVE","dataType":"FLOAT32","unit":"Current 'Knock Correction Advance Max' Map Value (degrees)","factor":1.0,"offset":0.0,"rows":1,"cols":1},{"name":"Rough Correction Learning Delay (Increasing) ","address":845964,"type":"CURVE","dataType":"UWORD","unit":"Rough Correction (IAM) Positive Learning Delay (counter threshold)","factor":1.0,"offset":0.0,"yAxis":{"type":"COM_AXIS","points":10,"min":0,"max":0,"unit":"","address":845924,"dataType":"UWORD","factor":1.0,"offset":0.0},"rows":1,"cols":10},{"name":"Advance Multiplier (Initial)","address":842044,"type":"CURVE","dataType":"FLOAT32","unit":"Ignition Advance Multiplier (IAM)","factor":1.0,"offset":0.0,"rows":1,"cols":1},{"name":"Advance Multiplier Step Value","address":842048,"type":"CURVE","dataType":"FLOAT32","unit":"change in multiplier","factor":1.0,"offset":0.0,"rows":1,"cols":1},{"name":"Intake Cam Advance Angle Cruise (AVCS)","address":874668,"type":"MAP","dataType":"UWORD","unit":"Advance (degrees)","factor":0.0054931640625,"offset":0.0,"xAxis":{"type":"COM_AXIS","points":15,"min":0,"max":0,"unit":"","address":874544,"dataType":"UWORD","factor":1.0,"offset":0.0},"yAxis":{"type":"COM_AXIS","points":16,"min":0,"max":0,"unit":"","address":874604,"dataType":"UWORD","factor":1.0,"offset":0.0},"rows":16,"cols":15},{"name":"Intake Cam Advance Angle Non-Cruise (AVCS)","address":875272,"type":"MAP","dataType":"UWORD","unit":"Advance (degrees)","factor":0.0054931640625,"offset":0.0,"xAxis":{"type":"COM_AXIS","points":15,"min":0,"max":0,"unit":"","address":875148,"dataType":"UWORD","factor":1.0,"offset":0.0},"yAxis":{"type":"COM_AXIS","points":16,"min":0,"max":0,"unit":"","address":875208,"dataType":"UWORD","factor":1.0,"offset":0.0},"rows":16,"cols":15},{"name":"Requested Torque A (Accelerator Pedal) SI-DRIVE Sport","address":906156,"type":"MAP","dataType":"UWORD","unit":"Requested Torque (raw ecu value)","factor":0.0078125,"offset":0.0,"xAxis":{"type":"COM_AXIS","points":20,"min":0,"max":0,"unit":"","address":905996,"dataType":"UWORD","factor":1.0,"offset":0.0},"yAxis":{"type":"COM_AXIS","points":20,"min":0,"max":0,"unit":"","address":906076,"dataType":"UWORD","factor":1.0,"offset":0.0},"rows":20,"cols":20},{"name":"Requested Torque B (Accelerator Pedal) SI-DRIVE Sport","address":909036,"type":"MAP","dataType":"UWORD","unit":"Requested Torque (raw ecu value)","factor":0.0078125,"offset":0.0,"xAxis":{"type":"COM_AXIS","points":20,"min":0,"max":0,"unit":"","address":908876,"dataType":"UWORD","factor":1.0,"offset":0.0},"yAxis":{"type":"COM_AXIS","points":20,"min":0,"max":0,"unit":"","address":908956,"dataType":"UWORD","factor":1.0,"offset":0.0},"rows":20,"cols":20},{"name":"Requested Torque A (Accelerator Pedal) SI-DRIVE Sport Sharp","address":907116,"type":"MAP","dataType":"UWORD","unit":"Requested Torque (raw ecu value)","factor":0.0078125,"offset":0.0,"xAxis":{"type":"COM_AXIS","points":20,"min":0,"max":0,"unit":"","address":906956,"dataType":"UWORD","factor":1.0,"offset":0.0},"yAxis":{"type":"COM_AXIS","points":20,"min":0,"max":0,"unit":"","address":907036,"dataType":"UWORD","factor":1.0,"offset":0.0},"rows":20,"cols":20},{"name":"Requested Torque B (Accelerator Pedal) SI-DRIVE Sport Sharp","address":909996,"type":"MAP","dataType":"UWORD","unit":"Requested Torque (raw ecu value)","factor":0.0078125,"offset":0.0,"xAxis":{"type":"COM_AXIS","points":20,"min":0,"max":0,"unit":"","address":909836,"dataType":"UWORD","factor":1.0,"offset":0.0},"yAxis":{"type":"COM_AXIS","points":20,"min":0,"max":0,"unit":"","address":909916,"dataType":"UWORD","factor":1.0,"offset":0.0},"rows":20,"cols":20},{"name":"Requested Torque A (Accelerator Pedal) SI-DRIVE Intelligent","address":908076,"type":"MAP","dataType":"UWORD","unit":"Requested Torque (raw ecu value)","factor":0.0078125,"offset":0.0,"xAxis":{"type":"COM_AXIS","points":20,"min":0,"max":0,"unit":"","address":907916,"dataType":"UWORD","factor":1.0,"offset":0.0},"yAxis":{"type":"COM_AXIS","points":20,"min":0,"max":0,"unit":"","address":907996,"dataType":"UWORD","factor":1.0,"offset":0.0},"rows":20,"cols":20},{"name":"Requested Torque B (Accelerator Pedal) SI-DRIVE Intelligent","address":910956,"type":"MAP","dataType":"UWORD","unit":"Requested Torque (raw ecu value)","factor":0.0078125,"offset":0.0,"xAxis":{"type":"COM_AXIS","points":20,"min":0,"max":0,"unit":"","address":910796,"dataType":"UWORD","factor":1.0,"offset":0.0},"yAxis":{"type":"COM_AXIS","points":20,"min":0,"max":0,"unit":"","address":910876,"dataType":"UWORD","factor":1.0,"offset":0.0},"rows":20,"cols":20},{"name":"Requested Torque Base (RPM)","address":903228,"type":"CURVE","dataType":"UWORD","unit":"Requested Torque (raw ecu value)","factor":0.0078125,"offset":0.0,"yAxis":{"type":"COM_AXIS","points":16,"min":0,"max":0,"unit":"","address":903164,"dataType":"UWORD","factor":1.0,"offset":0.0},"rows":1,"cols":16},{"name":"Target Throttle Plate Position Cruise (Requested Torque Ratio)","address":904408,"type":"MAP","dataType":"UWORD","unit":"Target Throttle Plate Opening Angle (%)","factor":0.002270655357,"offset":0.0,"xAxis":{"type":"COM_AXIS","points":11,"min":0,"max":0,"unit":"","address":904300,"dataType":"UWORD","factor":1.0,"offset":0.0},"yAxis":{"type":"COM_AXIS","points":16,"min":0,"max":0,"unit":"","address":904344,"dataType":"UWORD","factor":1.0,"offset":0.0},"rows":16,"cols":11},{"name":"Target Throttle Plate Position Non-Cruise (Requested Torque Ratio)","address":904868,"type":"MAP","dataType":"UWORD","unit":"Target Throttle Plate Opening Angle (%)","factor":0.002270655357,"offset":0.0,"xAxis":{"type":"COM_AXIS","points":11,"min":0,"max":0,"unit":"","address":904760,"dataType":"UWORD","factor":1.0,"offset":0.0},"yAxis":{"type":"COM_AXIS","points":16,"min":0,"max":0,"unit":"","address":904804,"dataType":"UWORD","factor":1.0,"offset":0.0},"rows":16,"cols":11},{"name":"Target Throttle Plate Position Maximum (Requested Torque Ratio)","address":905328,"type":"MAP","dataType":"UWORD","unit":"Target Throttle Plate Opening Angle (%)","factor":0.002270655357,"offset":0.0,"xAxis":{"type":"COM_AXIS","points":11,"min":0,"max":0,"unit":"","address":905220,"dataType":"UWORD","factor":1.0,"offset":0.0},"yAxis":{"type":"COM_AXIS","points":16,"min":0,"max":0,"unit":"","address":905264,"dataType":"UWORD","factor":1.0,"offset":0.0},"rows":16,"cols":11},{"name":"Rev Limit (Fuel Cut)","address":816900,"type":"CURVE","dataType":"FLOAT32","unit":"Engine Speed (RPM)","factor":1.0,"offset":0.0,"rows":1,"cols":2},{"name":"Rev Limit Fuel Resume (Boost)","address":816908,"type":"CURVE","dataType":"FLOAT32","unit":"Manifold Pressure (psi relative sea level)","factor":0.01933677000000067,"offset":-14.6959452,"rows":1,"cols":1},{"name":"Speed Limiting Enable (Fuel Cut)","address":816976,"type":"CURVE","dataType":"FLOAT32","unit":"Vehicle Speed (MPH)","factor":0.621,"offset":0.0,"rows":1,"cols":1},{"name":"Speed Limiting Disable (Fuel Cut)","address":816984,"type":"CURVE","dataType":"FLOAT32","unit":"Vehicle Speed (MPH)","factor":0.621,"offset":0.0,"rows":1,"cols":1},{"name":"Speed Limiting A (Throttle) SI-DRIVE Sport/Sport Sharp","address":902724,"type":"CURVE","dataType":"FLOAT32","unit":"Vehicle Speed (MPH)","factor":0.621,"offset":0.0,"rows":1,"cols":2},{"name":"Speed Limiting B (Throttle) SI-DRIVE Sport/Sport Sharp","address":902748,"type":"CURVE","dataType":"FLOAT32","unit":"Vehicle Speed (MPH)","factor":0.621,"offset":0.0,"rows":1,"cols":2},{"name":"Speed Limiting (Throttle) SI-DRIVE Intelligent","address":902736,"type":"CURVE","dataType":"FLOAT32","unit":"Vehicle Speed (MPH)","factor":0.621,"offset":0.0,"rows":1,"cols":2},{"name":"Intake Temp Sensor Scaling","address":866980,"type":"CURVE","dataType":"FLOAT32","unit":"Temperature (Degrees F)","factor":1.7999999999999972,"offset":32.0,"yAxis":{"type":"COM_AXIS","points":30,"min":0,"max":0,"unit":"","address":866860,"dataType":"UWORD","factor":1.0,"offset":0.0},"rows":1,"cols":30},{"name":"Coolant Temp Sensor Scaling","address":866748,"type":"CURVE","dataType":"FLOAT32","unit":"Temperature (Degrees F)","factor":1.7999999999999972,"offset":32.0,"yAxis":{"type":"COM_AXIS","points":28,"min":0,"max":0,"unit":"","address":866636,"dataType":"UWORD","factor":1.0,"offset":0.0},"rows":1,"cols":28},{"name":"Radiator Fan Modes A (ECT)","address":868420,"type":"CURVE","dataType":"FLOAT32","unit":"Coolant Temp (Degrees F)","factor":1.7999999999999972,"offset":32.0,"rows":1,"cols":4},{"name":"Radiator Fan Modes B (ECT)","address":868436,"type":"CURVE","dataType":"FLOAT32","unit":"Coolant Temp (Degrees F)","factor":1.7999999999999972,"offset":32.0,"rows":1,"cols":4},{"name":"Radiator Fan Modes (Veh. Speed)","address":868452,"type":"CURVE","dataType":"FLOAT32","unit":"Vehicle Speed (MPH)","factor":0.621,"offset":0.0,"rows":1,"cols":6},{"name":"Idle Speed Target A","address":859590,"type":"CURVE","dataType":"UWORD","unit":"Engine Speed (RPM)","factor":0.1953125,"offset":0.0,"yAxis":{"type":"COM_AXIS","points":16,"min":0,"max":0,"unit":"","address":857876,"dataType":"UWORD","factor":1.0,"offset":0.0},"rows":1,"cols":16},{"name":"Idle Speed Target B","address":859654,"type":"CURVE","dataType":"UWORD","unit":"Engine Speed (RPM)","factor":0.1953125,"offset":0.0,"yAxis":{"type":"COM_AXIS","points":16,"min":0,"max":0,"unit":"","address":857876,"dataType":"UWORD","factor":1.0,"offset":0.0},"rows":1,"cols":16},{"name":"Idle Speed Target C","address":859718,"type":"CURVE","dataType":"UWORD","unit":"Engine Speed (RPM)","factor":0.1953125,"offset":0.0,"yAxis":{"type":"COM_AXIS","points":16,"min":0,"max":0,"unit":"","address":857876,"dataType":"UWORD","factor":1.0,"offset":0.0},"rows":1,"cols":16},{"name":"Idle Speed Target D","address":859750,"type":"CURVE","dataType":"UWORD","unit":"Engine Speed (RPM)","factor":0.1953125,"offset":0.0,"yAxis":{"type":"COM_AXIS","points":16,"min":0,"max":0,"unit":"","address":857876,"dataType":"UWORD","factor":1.0,"offset":0.0},"rows":1,"cols":16}]}